hardware/ALU.v
// ALU block
module ALU(
    input [3:0] alu_ctl, 
    input [15:0] a, b,
    output reg [15:0] result,
    output reg [4:0] status 
    // Status bits representations [ zero | negative | carry | overflow ]
);
    // Addition Operation
    task add;
        input [15:0] a, b;
        output [15:0] result;
        output reg [3:0] status;
        reg [16:0] tmp;
        reg zero, negative, carry, overflow;
        begin
            
            tmp = a + b;
            result = tmp[15:0];
            negative = tmp[15];
            carry = tmp[16];
            zero = (tmp[15:0] == 16'h0);

            /* Overflow detection
                Checks if the result has already overflowed
                or the result is about the get overflown
            */
            overflow = (a[15] & b[15] & ~result[15]) | 
                                (~a[15] & ~b[15] & result[15]);

            status[0] = overflow;
            status[1] = carry;
            status[2] = negative;
            status[3] = zero;
        end
    endtask

    // Subtraction Operations
    task sub;
        input [15:0] a, b;
        output reg [15:0] result;
        output reg [3:0] status;
        reg [16:0] tmp;
        reg zero, negative, carry, underflow;
        begin
            tmp = a - b; // Same thing as => a + (~b + 1'b1);
            
            result = tmp[15:0];
            negative = tmp[15];
            carry = tmp[16];
            zero = (tmp[15:0] == 16'h0);
            

            /* Underflow detection
                Checks if the result has already overflowed
                or the result is about the get overflown
            */
            underflow = (a[15] & b[15] & ~result[15]) | 
                                (~a[15] & ~b[15] & result[15]);

            status[0] = underflow;
            status[1] = carry;
            status[2] = negative;
            status[3] = zero;
        end
    endtask
    
    always @(*) begin 
        status = 5'd0;
        case (alu_ctl)
            `ADD: add(a, b, result, status[3:0]);
            `SUB: sub(a, b, result, status[3:0]);
            default: 
                begin 
                    result = 16'hDEAD; // Should never hit
                    status[4] = 1'b1; // Returns invalid alu operation
                end
        endcase
    end
endmodule

tests/ALU/add_tb.v
module addition_tb();
    reg         clk;
    reg  [4:0]  counter;
    reg  signed [15:0] a, b;   // signed to handle negative tests
    wire [15:0] result;
    wire [4:0]  status;

    ALU add_operation(
        .alu_ctl(`ADD),
        .a(a), .b(b),
        .result(result),
        .status(status)
    );

    initial begin
        $dumpfile("addition.vcd");
        $dumpvars(0, addition_tb);
        clk     = 1'b0;
        counter = 5'd0;
        a       = 16'd0;
        b       = 16'd0;
        #20000;
        $finish;
    end

    always #5 clk = ~clk;

    always @(posedge clk)
        counter <= counter + 1;

    always @(*) begin       
        case (counter)
            5'd1: begin a <= 16'd1;     b <= 16'd1;    end
            5'd2: begin a <= 16'hFFFF;  b <= 16'd1;    end  
            5'd3: begin a <= 16'hFFFF;  b <= 16'hFFFF; end
            5'd4: begin a <= 16'd15;    b <= 16'd37;   end
            5'd5: begin a <= 16'd37;    b <= 16'd15;   end
            5'd6: begin a <= -16'd15;   b <= 16'd37;   end  
            default: begin a <= 16'd0;  b <= 16'd0;    end
        endcase
    end

endmodule

addition.vcd
$date
	Wed May  6 17:22:16 2026
$end
$version
	Icarus Verilog
$end
$timescale
	1s
$end
$scope module addition_tb $end
$var wire 5 ! status [4:0] $end
$var wire 16 " result [15:0] $end
$var reg 16 # a [15:0] $end
$var reg 16 $ b [15:0] $end
$var reg 1 % clk $end
$var reg 5 & counter [4:0] $end
$scope module add_operation $end
$var wire 16 ' a [15:0] $end
$var wire 4 ( alu_ctl [3:0] $end
$var wire 16 ) b [15:0] $end
$var reg 16 * result [15:0] $end
$var reg 5 + status [4:0] $end
$scope task add $end
$var reg 16 , a [15:0] $end
$var reg 16 - b [15:0] $end
$var reg 1 . carry $end
$var reg 1 / negative $end
$var reg 1 0 overflow $end
$var reg 16 1 result [15:0] $end
$var reg 4 2 status [3:0] $end
$var reg 17 3 tmp [16:0] $end
$var reg 1 4 zero $end
$upscope $end
$scope task sub $end
$var reg 16 5 a [15:0] $end
$var reg 16 6 b [15:0] $end
$var reg 1 7 carry $end
$var reg 1 8 negative $end
$var reg 16 9 result [15:0] $end
$var reg 4 : status [3:0] $end
$var reg 17 ; tmp [16:0] $end
$var reg 1 < underflow $end
$var reg 1 = zero $end
$upscope $end
$upscope $end
$upscope $end
$enddefinitions $end
$comment Show the parameter values. $end
$dumpall
$end
#0
$dumpvars
x=
x<
bx ;
bx :
bx 9
x8
x7
bx 6
bx 5
14
b0 3
b1000 2
b0 1
00
0/
0.
b0 -
b0 ,
b1000 +
b0 *
b0 )
b1 (
b0 '
b0 &
0%
b0 $
b0 #
b0 "
b1000 !
$end
#5
b10 "
b10 *
b0 2
04
b10 1
b10 3
b1 -
b1 ,
b0 !
b0 +
b1 $
b1 )
b1 #
b1 '
b1 &
1%
#10
0%
#15
b1010 !
b1010 +
b0 "
b0 *
b1010 2
14
1.
b0 1
b10000000000000000 3
b1111111111111111 ,
b1111111111111111 #
b1111111111111111 '
b10 &
1%
#20
0%
#25
b1111111111111110 "
b1111111111111110 *
b110 2
04
1/
b1111111111111110 1
b11111111111111110 3
b1111111111111111 -
b110 !
b110 +
b1111111111111111 $
b1111111111111111 )
b11 &
1%
#30
0%
#35
b110100 "
b110100 *
b0 2
0.
0/
b110100 1
b110100 3
b100101 -
b1111 ,
b0 !
b0 +
b100101 $
b100101 )
b1111 #
b1111 '
b100 &
1%
#40
0%
#45
b1111 -
b100101 ,
b1111 $
b1111 )
b100101 #
b100101 '
b101 &
1%
#50
0%
#55
b10 !
b10 +
b10110 "
b10110 *
b10 2
1.
b10110 1
b10000000000010110 3
b100101 -
b1111111111110001 ,
b100101 $
b100101 )
b1111111111110001 #
b1111111111110001 '
b110 &
1%
#60
0%
#65
b0 "
b0 *
b1000 2
14
0.
b0 1
b0 3
b0 -
b0 ,
b1000 !
b1000 +
b0 $
b0 )
b0 #
b0 '
b111 &
1%
#70
0%
#75
b1000 &
1%
#80
0%
#85
b1001 &
1%
#90
0%
#95
b1010 &
1%
#100
0%
#105
b1011 &
1%
#110
0%
#115
b1100 &
1%
#120
0%
#125
b1101 &
1%
#130
0%
#135
b1110 &
1%
#140
0%
#145
b1111 &
1%
#150
0%
#155
b10000 &
1%
#160
0%
#165
b10001 &
1%
#170
0%
#175
b10010 &
1%
#180
0%
#185
b10011 &
1%
#190
0%
#195
b10100 &
1%
#200
0%
#205
b10101 &
1%
#210
0%
#215
b10110 &
1%
#220
0%
#225
b10111 &
1%
#230
0%
#235
b11000 &
1%
#240
0%
#245
b11001 &
1%
#250
0%
#255
b11010 &
1%
#260
0%
#265
b11011 &
1%
#270
0%
#275
b11100 &
1%
#280
0%
#285
b11101 &
1%
#290
0%
#295
b11110 &
1%
#300
0%
#305
b11111 &
1%
#310
0%
#315
b0 &
1%
#320
0%
#325
b10 "
b10 *
b0 2
04
b10 1
b10 3
b1 -
b1 ,
b0 !
b0 +
b1 $
b1 )
b1 #
b1 '
b1 &
1%
#330
0%
#335
b1010 !
b1010 +
b0 "
b0 *
b1010 2
14
1.
b0 1
b10000000000000000 3
b1111111111111111 ,
b1111111111111111 #
b1111111111111111 '
b10 &
1%
#340
0%
#345
b1111111111111110 "
b1111111111111110 *
b110 2
04
1/
b1111111111111110 1
b11111111111111110 3
b1111111111111111 -
b110 !
b110 +
b1111111111111111 $
b1111111111111111 )
b11 &
1%
#350
0%
#355
b110100 "
b110100 *
b0 2
0.
0/
b110100 1
b110100 3
b100101 -
b1111 ,
b0 !
b0 +
b100101 $
b100101 )
b1111 #
b1111 '
b100 &
1%
#360
0%
#365
b1111 -
b100101 ,
b1111 $
b1111 )
b100101 #
b100101 '
b101 &
1%
#370
0%
#375
b10 !
b10 +
b10110 "
b10110 *
b10 2
1.
b10110 1
b10000000000010110 3
b100101 -
b1111111111110001 ,
b100101 $
b100101 )
b1111111111110001 #
b1111111111110001 '
b110 &
1%
#380
0%
#385
b0 "
b0 *
b1000 2
14
0.
b0 1
b0 3
b0 -
b0 ,
b1000 !
b1000 +
b0 $
b0 )
b0 #
b0 '
b111 &
1%
#390
0%
#395
b1000 &
1%
#400
0%
#405
b1001 &
1%
#410
0%
#415
b1010 &
1%
#420
0%
#425
b1011 &
1%
#430
0%
#435
b1100 &
1%
#440
0%
#445
b1101 &
1%
#450
0%
#455
b1110 &
1%
#460
0%
#465
b1111 &
1%
#470
0%
#475
b10000 &
1%
#480
0%
#485
b10001 &
1%
#490
0%
#495
b10010 &
1%
#500
0%
#505
b10011 &
1%
#510
0%
#515
b10100 &
1%
#520
0%
#525
b10101 &
1%
#530
0%
#535
b10110 &
1%
#540
0%
#545
b10111 &
1%
#550
0%
#555
b11000 &
1%
#560
0%
#565
b11001 &
1%
#570
0%
#575
b11010 &
1%
#580
0%
#585
b11011 &
1%
#590
0%
#595
b11100 &
1%
#600
0%
#605
b11101 &
1%
#610
0%
#615
b11110 &
1%
#620
0%
#625
b11111 &
1%
#630
0%
#635
b0 &
1%
#640
0%
#645
b10 "
b10 *
b0 2
04
b10 1
b10 3
b1 -
b1 ,
b0 !
b0 +
b1 $
b1 )
b1 #
b1 '
b1 &
1%
#650
0%
#655
b1010 !
b1010 +
b0 "
b0 *
b1010 2
14
1.
b0 1
b10000000000000000 3
b1111111111111111 ,
b1111111111111111 #
b1111111111111111 '
b10 &
1%
#660
0%
#665
b1111111111111110 "
b1111111111111110 *
b110 2
04
1/
b1111111111111110 1
b11111111111111110 3
b1111111111111111 -
b110 !
b110 +
b1111111111111111 $
b1111111111111111 )
b11 &
1%
#670
0%
#675
b110100 "
b110100 *
b0 2
0.
0/
b110100 1
b110100 3
b100101 -
b1111 ,
b0 !
b0 +
b100101 $
b100101 )
b1111 #
b1111 '
b100 &
1%
#680
0%
#685
b1111 -
b100101 ,
b1111 $
b1111 )
b100101 #
b100101 '
b101 &
1%
#690
0%
#695
b10 !
b10 +
b10110 "
b10110 *
b10 2
1.
b10110 1
b10000000000010110 3
b100101 -
b1111111111110001 ,
b100101 $
b100101 )
b1111111111110001 #
b1111111111110001 '
b110 &
1%
#700
0%
#705
b0 "
b0 *
b1000 2
14
0.
b0 1
b0 3
b0 -
b0 ,
b1000 !
b1000 +
b0 $
b0 )
b0 #
b0 '
b111 &
1%
#710
0%
#715
b1000 &
1%
#720
0%
#725
b1001 &
1%
#730
0%
#735
b1010 &
1%
#740
0%
#745
b1011 &
1%
#750
0%
#755
b1100 &
1%
#760
0%
#765
b1101 &
1%
#770
0%
#775
b1110 &
1%
#780
0%
#785
b1111 &
1%
#790
0%
#795
b10000 &
1%
#800
0%
#805
b10001 &
1%
#810
0%
#815
b10010 &
1%
#820
0%
#825
b10011 &
1%
#830
0%
#835
b10100 &
1%
#840
0%
#845
b10101 &
1%
#850
0%
#855
b10110 &
1%
#860
0%
#865
b10111 &
1%
#870
0%
#875
b11000 &
1%
#880
0%
#885
b11001 &
1%
#890
0%
#895
b11010 &
1%
#900
0%
#905
b11011 &
1%
#910
0%
#915
b11100 &
1%
#920
0%
#925
b11101 &
1%
#930
0%
#935
b11110 &
1%
#940
0%
#945
b11111 &
1%
#950
0%
#955
b0 &
1%
#960
0%
#965
b10 "
b10 *
b0 2
04
b10 1
b10 3
b1 -
b1 ,
b0 !
b0 +
b1 $
b1 )
b1 #
b1 '
b1 &
1%
#970
0%
#975
b1010 !
b1010 +
b0 "
b0 *
b1010 2
14
1.
b0 1
b10000000000000000 3
b1111111111111111 ,
b1111111111111111 #
b1111111111111111 '
b10 &
1%
#980
0%
#985
b1111111111111110 "
b1111111111111110 *
b110 2
04
1/
b1111111111111110 1
b11111111111111110 3
b1111111111111111 -
b110 !
b110 +
b1111111111111111 $
b1111111111111111 )
b11 &
1%
#990
0%
#995
b110100 "
b110100 *
b0 2
0.
0/
b110100 1
b110100 3
b100101 -
b1111 ,
b0 !
b0 +
b100101 $
b100101 )
b1111 #
b1111 '
b100 &
1%
#1000
0%
#1005
b1111 -
b100101 ,
b1111 $
b1111 )
b100101 #
b100101 '
b101 &
1%
#1010
0%
#1015
b10 !
b10 +
b10110 "
b10110 *
b10 2
1.
b10110 1
b10000000000010110 3
b100101 -
b1111111111110001 ,
b100101 $
b100101 )
b1111111111110001 #
b1111111111110001 '
b110 &
1%
#1020
0%
#1025
b0 "
b0 *
b1000 2
14
0.
b0 1
b0 3
b0 -
b0 ,
b1000 !
b1000 +
b0 $
b0 )
b0 #
b0 '
b111 &
1%
#1030
0%
#1035
b1000 &
1%
#1040
0%
#1045
b1001 &
1%
#1050
0%
#1055
b1010 &
1%
#1060
0%
#1065
b1011 &
1%
#1070
0%
#1075
b1100 &
1%
#1080
0%
#1085
b1101 &
1%
#1090
0%
#1095
b1110 &
1%
#1100
0%
#1105
b1111 &
1%
#1110
0%
#1115
b10000 &
1%
#1120
0%
#1125
b10001 &
1%
#1130
0%
#1135
b10010 &
1%
#1140
0%
#1145
b10011 &
1%
#1150
0%
#1155
b10100 &
1%
#1160
0%
#1165
b10101 &
1%
#1170
0%
#1175
b10110 &
1%
#1180
0%
#1185
b10111 &
1%
#1190
0%
#1195
b11000 &
1%
#1200
0%
#1205
b11001 &
1%
#1210
0%
#1215
b11010 &
1%
#1220
0%
#1225
b11011 &
1%
#1230
0%
#1235
b11100 &
1%
#1240
0%
#1245
b11101 &
1%
#1250
0%
#1255
b11110 &
1%
#1260
0%
#1265
b11111 &
1%
#1270
0%
#1275
b0 &
1%
#1280
0%
#1285
b10 "
b10 *
b0 2
04
b10 1
b10 3
b1 -
b1 ,
b0 !
b0 +
b1 $
b1 )
b1 #
b1 '
b1 &
1%
#1290
0%
#1295
b1010 !
b1010 +
b0 "
b0 *
b1010 2
14
1.
b0 1
b10000000000000000 3
b1111111111111111 ,
b1111111111111111 #
b1111111111111111 '
b10 &
1%
#1300
0%
#1305
b1111111111111110 "
b1111111111111110 *
b110 2
04
1/
b1111111111111110 1
b11111111111111110 3
b1111111111111111 -
b110 !
b110 +
b1111111111111111 $
b1111111111111111 )
b11 &
1%
#1310
0%
#1315
b110100 "
b110100 *
b0 2
0.
0/
b110100 1
b110100 3
b100101 -
b1111 ,
b0 !
b0 +
b100101 $
b100101 )
b1111 #
b1111 '
b100 &
1%
#1320
0%
#1325
b1111 -
b100101 ,
b1111 $
b1111 )
b100101 #
b100101 '
b101 &
1%
#1330
0%
#1335
b10 !
b10 +
b10110 "
b10110 *
b10 2
1.
b10110 1
b10000000000010110 3
b100101 -
b1111111111110001 ,
b100101 $
b100101 )
b1111111111110001 #
b1111111111110001 '
b110 &
1%
#1340
0%
#1345
b0 "
b0 *
b1000 2
14
0.
b0 1
b0 3
b0 -
b0 ,
b1000 !
b1000 +
b0 $
b0 )
b0 #
b0 '
b111 &
1%
#1350
0%
#1355
b1000 &
1%
#1360
0%
#1365
b1001 &
1%
#1370
0%
#1375
b1010 &
1%
#1380
0%
#1385
b1011 &
1%
#1390
0%
#1395
b1100 &
1%
#1400
0%
#1405
b1101 &
1%
#1410
0%
#1415
b1110 &
1%
#1420
0%
#1425
b1111 &
1%
#1430
0%
#1435
b10000 &
1%
#1440
0%
#1445
b10001 &
1%
#1450
0%
#1455
b10010 &
1%
#1460
0%
#1465
b10011 &
1%
#1470
0%
#1475
b10100 &
1%
#1480
0%
#1485
b10101 &
1%
#1490
0%
#1495
b10110 &
1%
#1500
0%
#1505
b10111 &
1%
#1510
0%
#1515
b11000 &
1%
#1520
0%
#1525
b11001 &
1%
#1530
0%
#1535
b11010 &
1%
#1540
0%
#1545
b11011 &
1%
#1550
0%
#1555
b11100 &
1%
#1560
0%
#1565
b11101 &
1%
#1570
0%
#1575
b11110 &
1%
#1580
0%
#1585
b11111 &
1%
#1590
0%
#1595
b0 &
1%
#1600
0%
#1605
b10 "
b10 *
b0 2
04
b10 1
b10 3
b1 -
b1 ,
b0 !
b0 +
b1 $
b1 )
b1 #
b1 '
b1 &
1%
#1610
0%
#1615
b1010 !
b1010 +
b0 "
b0 *
b1010 2
14
1.
b0 1
b10000000000000000 3
b1111111111111111 ,
b1111111111111111 #
b1111111111111111 '
b10 &
1%
#1620
0%
#1625
b1111111111111110 "
b1111111111111110 *
b110 2
04
1/
b1111111111111110 1
b11111111111111110 3
b1111111111111111 -
b110 !
b110 +
b1111111111111111 $
b1111111111111111 )
b11 &
1%
#1630
0%
#1635
b110100 "
b110100 *
b0 2
0.
0/
b110100 1
b110100 3
b100101 -
b1111 ,
b0 !
b0 +
b100101 $
b100101 )
b1111 #
b1111 '
b100 &
1%
#1640
0%
#1645
b1111 -
b100101 ,
b1111 $
b1111 )
b100101 #
b100101 '
b101 &
1%
#1650
0%
#1655
b10 !
b10 +
b10110 "
b10110 *
b10 2
1.
b10110 1
b10000000000010110 3
b100101 -
b1111111111110001 ,
b100101 $
b100101 )
b1111111111110001 #
b1111111111110001 '
b110 &
1%
#1660
0%
#1665
b0 "
b0 *
b1000 2
14
0.
b0 1
b0 3
b0 -
b0 ,
b1000 !
b1000 +
b0 $
b0 )
b0 #
b0 '
b111 &
1%
#1670
0%
#1675
b1000 &
1%
#1680
0%
#1685
b1001 &
1%
#1690
0%
#1695
b1010 &
1%
#1700
0%
#1705
b1011 &
1%
#1710
0%
#1715
b1100 &
1%
#1720
0%
#1725
b1101 &
1%
#1730
0%
#1735
b1110 &
1%
#1740
0%
#1745
b1111 &
1%
#1750
0%
#1755
b10000 &
1%
#1760
0%
#1765
b10001 &
1%
#1770
0%
#1775
b10010 &
1%
#1780
0%
#1785
b10011 &
1%
#1790
0%
#1795
b10100 &
1%
#1800
0%
#1805
b10101 &
1%
#1810
0%
#1815
b10110 &
1%
#1820
0%
#1825
b10111 &
1%
#1830
0%
#1835
b11000 &
1%
#1840
0%
#1845
b11001 &
1%
#1850
0%
#1855
b11010 &
1%
#1860
0%
#1865
b11011 &
1%
#1870
0%
#1875
b11100 &
1%
#1880
0%
#1885
b11101 &
1%
#1890
0%
#1895
b11110 &
1%
#1900
0%
#1905
b11111 &
1%
#1910
0%
#1915
b0 &
1%
#1920
0%
#1925
b10 "
b10 *
b0 2
04
b10 1
b10 3
b1 -
b1 ,
b0 !
b0 +
b1 $
b1 )
b1 #
b1 '
b1 &
1%
#1930
0%
#1935
b1010 !
b1010 +
b0 "
b0 *
b1010 2
14
1.
b0 1
b10000000000000000 3
b1111111111111111 ,
b1111111111111111 #
b1111111111111111 '
b10 &
1%
#1940
0%
#1945
b1111111111111110 "
b1111111111111110 *
b110 2
04
1/
b1111111111111110 1
b11111111111111110 3
b1111111111111111 -
b110 !
b110 +
b1111111111111111 $
b1111111111111111 )
b11 &
1%
#1950
0%
#1955
b110100 "
b110100 *
b0 2
0.
0/
b110100 1
b110100 3
b100101 -
b1111 ,
b0 !
b0 +
b100101 $
b100101 )
b1111 #
b1111 '
b100 &
1%
#1960
0%
#1965
b1111 -
b100101 ,
b1111 $
b1111 )
b100101 #
b100101 '
b101 &
1%
#1970
0%
#1975
b10 !
b10 +
b10110 "
b10110 *
b10 2
1.
b10110 1
b10000000000010110 3
b100101 -
b1111111111110001 ,
b100101 $
b100101 )
b1111111111110001 #
b1111111111110001 '
b110 &
1%
#1980
0%
#1985
b0 "
b0 *
b1000 2
14
0.
b0 1
b0 3
b0 -
b0 ,
b1000 !
b1000 +
b0 $
b0 )
b0 #
b0 '
b111 &
1%
#1990
0%
#1995
b1000 &
1%
#2000
0%
#2005
b1001 &
1%
#2010
0%
#2015
b1010 &
1%
#2020
0%
#2025
b1011 &
1%
#2030
0%
#2035
b1100 &
1%
#2040
0%
#2045
b1101 &
1%
#2050
0%
#2055
b1110 &
1%
#2060
0%
#2065
b1111 &
1%
#2070
0%
#2075
b10000 &
1%
#2080
0%
#2085
b10001 &
1%
#2090
0%
#2095
b10010 &
1%
#2100
0%
#2105
b10011 &
1%
#2110
0%
#2115
b10100 &
1%
#2120
0%
#2125
b10101 &
1%
#2130
0%
#2135
b10110 &
1%
#2140
0%
#2145
b10111 &
1%
#2150
0%
#2155
b11000 &
1%
#2160
0%
#2165
b11001 &
1%
#2170
0%
#2175
b11010 &
1%
#2180
0%
#2185
b11011 &
1%
#2190
0%
#2195
b11100 &
1%
#2200
0%
#2205
b11101 &
1%
#2210
0%
#2215
b11110 &
1%
#2220
0%
#2225
b11111 &
1%
#2230
0%
#2235
b0 &
1%
#2240
0%
#2245
b10 "
b10 *
b0 2
04
b10 1
b10 3
b1 -
b1 ,
b0 !
b0 +
b1 $
b1 )
b1 #
b1 '
b1 &
1%
#2250
0%
#2255
b1010 !
b1010 +
b0 "
b0 *
b1010 2
14
1.
b0 1
b10000000000000000 3
b1111111111111111 ,
b1111111111111111 #
b1111111111111111 '
b10 &
1%
#2260
0%
#2265
b1111111111111110 "
b1111111111111110 *
b110 2
04
1/
b1111111111111110 1
b11111111111111110 3
b1111111111111111 -
b110 !
b110 +
b1111111111111111 $
b1111111111111111 )
b11 &
1%
#2270
0%
#2275
b110100 "
b110100 *
b0 2
0.
0/
b110100 1
b110100 3
b100101 -
b1111 ,
b0 !
b0 +
b100101 $
b100101 )
b1111 #
b1111 '
b100 &
1%
#2280
0%
#2285
b1111 -
b100101 ,
b1111 $
b1111 )
b100101 #
b100101 '
b101 &
1%
#2290
0%
#2295
b10 !
b10 +
b10110 "
b10110 *
b10 2
1.
b10110 1
b10000000000010110 3
b100101 -
b1111111111110001 ,
b100101 $
b100101 )
b1111111111110001 #
b1111111111110001 '
b110 &
1%
#2300
0%
#2305
b0 "
b0 *
b1000 2
14
0.
b0 1
b0 3
b0 -
b0 ,
b1000 !
b1000 +
b0 $
b0 )
b0 #
b0 '
b111 &
1%
#2310
0%
#2315
b1000 &
1%
#2320
0%
#2325
b1001 &
1%
#2330
0%
#2335
b1010 &
1%
#2340
0%
#2345
b1011 &
1%
#2350
0%
#2355
b1100 &
1%
#2360
0%
#2365
b1101 &
1%
#2370
0%
#2375
b1110 &
1%
#2380
0%
#2385
b1111 &
1%
#2390
0%
#2395
b10000 &
1%
#2400
0%
#2405
b10001 &
1%
#2410
0%
#2415
b10010 &
1%
#2420
0%
#2425
b10011 &
1%
#2430
0%
#2435
b10100 &
1%
#2440
0%
#2445
b10101 &
1%
#2450
0%
#2455
b10110 &
1%
#2460
0%
#2465
b10111 &
1%
#2470
0%
#2475
b11000 &
1%
#2480
0%
#2485
b11001 &
1%
#2490
0%
#2495
b11010 &
1%
#2500
0%
#2505
b11011 &
1%
#2510
0%
#2515
b11100 &
1%
#2520
0%
#2525
b11101 &
1%
#2530
0%
#2535
b11110 &
1%
#2540
0%
#2545
b11111 &
1%
#2550
0%
#2555
b0 &
1%
#2560
0%
#2565
b10 "
b10 *
b0 2
04
b10 1
b10 3
b1 -
b1 ,
b0 !
b0 +
b1 $
b1 )
b1 #
b1 '
b1 &
1%
#2570
0%
#2575
b1010 !
b1010 +
b0 "
b0 *
b1010 2
14
1.
b0 1
b10000000000000000 3
b1111111111111111 ,
b1111111111111111 #
b1111111111111111 '
b10 &
1%
#2580
0%
#2585
b1111111111111110 "
b1111111111111110 *
b110 2
04
1/
b1111111111111110 1
b11111111111111110 3
b1111111111111111 -
b110 !
b110 +
b1111111111111111 $
b1111111111111111 )
b11 &
1%
#2590
0%
#2595
b110100 "
b110100 *
b0 2
0.
0/
b110100 1
b110100 3
b100101 -
b1111 ,
b0 !
b0 +
b100101 $
b100101 )
b1111 #
b1111 '
b100 &
1%
#2600
0%
#2605
b1111 -
b100101 ,
b1111 $
b1111 )
b100101 #
b100101 '
b101 &
1%
#2610
0%
#2615
b10 !
b10 +
b10110 "
b10110 *
b10 2
1.
b10110 1
b10000000000010110 3
b100101 -
b1111111111110001 ,
b100101 $
b100101 )
b1111111111110001 #
b1111111111110001 '
b110 &
1%
#2620
0%
#2625
b0 "
b0 *
b1000 2
14
0.
b0 1
b0 3
b0 -
b0 ,
b1000 !
b1000 +
b0 $
b0 )
b0 #
b0 '
b111 &
1%
#2630
0%
#2635
b1000 &
1%
#2640
0%
#2645
b1001 &
1%
#2650
0%
#2655
b1010 &
1%
#2660
0%
#2665
b1011 &
1%
#2670
0%
#2675
b1100 &
1%
#2680
0%
#2685
b1101 &
1%
#2690
0%
#2695
b1110 &
1%
#2700
0%
#2705
b1111 &
1%
#2710
0%
#2715
b10000 &
1%
#2720
0%
#2725
b10001 &
1%
#2730
0%
#2735
b10010 &
1%
#2740
0%
#2745
b10011 &
1%
#2750
0%
#2755
b10100 &
1%
#2760
0%
#2765
b10101 &
1%
#2770
0%
#2775
b10110 &
1%
#2780
0%
#2785
b10111 &
1%
#2790
0%
#2795
b11000 &
1%
#2800
0%
#2805
b11001 &
1%
#2810
0%
#2815
b11010 &
1%
#2820
0%
#2825
b11011 &
1%
#2830
0%
#2835
b11100 &
1%
#2840
0%
#2845
b11101 &
1%
#2850
0%
#2855
b11110 &
1%
#2860
0%
#2865
b11111 &
1%
#2870
0%
#2875
b0 &
1%
#2880
0%
#2885
b10 "
b10 *
b0 2
04
b10 1
b10 3
b1 -
b1 ,
b0 !
b0 +
b1 $
b1 )
b1 #
b1 '
b1 &
1%
#2890
0%
#2895
b1010 !
b1010 +
b0 "
b0 *
b1010 2
14
1.
b0 1
b10000000000000000 3
b1111111111111111 ,
b1111111111111111 #
b1111111111111111 '
b10 &
1%
#2900
0%
#2905
b1111111111111110 "
b1111111111111110 *
b110 2
04
1/
b1111111111111110 1
b11111111111111110 3
b1111111111111111 -
b110 !
b110 +
b1111111111111111 $
b1111111111111111 )
b11 &
1%
#2910
0%
#2915
b110100 "
b110100 *
b0 2
0.
0/
b110100 1
b110100 3
b100101 -
b1111 ,
b0 !
b0 +
b100101 $
b100101 )
b1111 #
b1111 '
b100 &
1%
#2920
0%
#2925
b1111 -
b100101 ,
b1111 $
b1111 )
b100101 #
b100101 '
b101 &
1%
#2930
0%
#2935
b10 !
b10 +
b10110 "
b10110 *
b10 2
1.
b10110 1
b10000000000010110 3
b100101 -
b1111111111110001 ,
b100101 $
b100101 )
b1111111111110001 #
b1111111111110001 '
b110 &
1%
#2940
0%
#2945
b0 "
b0 *
b1000 2
14
0.
b0 1
b0 3
b0 -
b0 ,
b1000 !
b1000 +
b0 $
b0 )
b0 #
b0 '
b111 &
1%
#2950
0%
#2955
b1000 &
1%
#2960
0%
#2965
b1001 &
1%
#2970
0%
#2975
b1010 &
1%
#2980
0%
#2985
b1011 &
1%
#2990
0%
#2995
b1100 &
1%
#3000
0%
#3005
b1101 &
1%
#3010
0%
#3015
b1110 &
1%
#3020
0%
#3025
b1111 &
1%
#3030
0%
#3035
b10000 &
1%
#3040
0%
#3045
b10001 &
1%
#3050
0%
#3055
b10010 &
1%
#3060
0%
#3065
b10011 &
1%
#3070
0%
#3075
b10100 &
1%
#3080
0%
#3085
b10101 &
1%
#3090
0%
#3095
b10110 &
1%
#3100
0%
#3105
b10111 &
1%
#3110
0%
#3115
b11000 &
1%
#3120
0%
#3125
b11001 &
1%
#3130
0%
#3135
b11010 &
1%
#3140
0%
#3145
b11011 &
1%
#3150
0%
#3155
b11100 &
1%
#3160
0%
#3165
b11101 &
1%
#3170
0%
#3175
b11110 &
1%
#3180
0%
#3185
b11111 &
1%
#3190
0%
#3195
b0 &
1%
#3200
0%
#3205
b10 "
b10 *
b0 2
04
b10 1
b10 3
b1 -
b1 ,
b0 !
b0 +
b1 $
b1 )
b1 #
b1 '
b1 &
1%
#3210
0%
#3215
b1010 !
b1010 +
b0 "
b0 *
b1010 2
14
1.
b0 1
b10000000000000000 3
b1111111111111111 ,
b1111111111111111 #
b1111111111111111 '
b10 &
1%
#3220
0%
#3225
b1111111111111110 "
b1111111111111110 *
b110 2
04
1/
b1111111111111110 1
b11111111111111110 3
b1111111111111111 -
b110 !
b110 +
b1111111111111111 $
b1111111111111111 )
b11 &
1%
#3230
0%
#3235
b110100 "
b110100 *
b0 2
0.
0/
b110100 1
b110100 3
b100101 -
b1111 ,
b0 !
b0 +
b100101 $
b100101 )
b1111 #
b1111 '
b100 &
1%
#3240
0%
#3245
b1111 -
b100101 ,
b1111 $
b1111 )
b100101 #
b100101 '
b101 &
1%
#3250
0%
#3255
b10 !
b10 +
b10110 "
b10110 *
b10 2
1.
b10110 1
b10000000000010110 3
b100101 -
b1111111111110001 ,
b100101 $
b100101 )
b1111111111110001 #
b1111111111110001 '
b110 &
1%
#3260
0%
#3265
b0 "
b0 *
b1000 2
14
0.
b0 1
b0 3
b0 -
b0 ,
b1000 !
b1000 +
b0 $
b0 )
b0 #
b0 '
b111 &
1%
#3270
0%
#3275
b1000 &
1%
#3280
0%
#3285
b1001 &
1%
#3290
0%
#3295
b1010 &
1%
#3300
0%
#3305
b1011 &
1%
#3310
0%
#3315
b1100 &
1%
#3320
0%
#3325
b1101 &
1%
#3330
0%
#3335
b1110 &
1%
#3340
0%
#3345
b1111 &
1%
#3350
0%
#3355
b10000 &
1%
#3360
0%
#3365
b10001 &
1%
#3370
0%
#3375
b10010 &
1%
#3380
0%
#3385
b10011 &
1%
#3390
0%
#3395
b10100 &
1%
#3400
0%
#3405
b10101 &
1%
#3410
0%
#3415
b10110 &
1%
#3420
0%
#3425
b10111 &
1%
#3430
0%
#3435
b11000 &
1%
#3440
0%
#3445
b11001 &
1%
#3450
0%
#3455
b11010 &
1%
#3460
0%
#3465
b11011 &
1%
#3470
0%
#3475
b11100 &
1%
#3480
0%
#3485
b11101 &
1%
#3490
0%
#3495
b11110 &
1%
#3500
0%
#3505
b11111 &
1%
#3510
0%
#3515
b0 &
1%
#3520
0%
#3525
b10 "
b10 *
b0 2
04
b10 1
b10 3
b1 -
b1 ,
b0 !
b0 +
b1 $
b1 )
b1 #
b1 '
b1 &
1%
#3530
0%
#3535
b1010 !
b1010 +
b0 "
b0 *
b1010 2
14
1.
b0 1
b10000000000000000 3
b1111111111111111 ,
b1111111111111111 #
b1111111111111111 '
b10 &
1%
#3540
0%
#3545
b1111111111111110 "
b1111111111111110 *
b110 2
04
1/
b1111111111111110 1
b11111111111111110 3
b1111111111111111 -
b110 !
b110 +
b1111111111111111 $
b1111111111111111 )
b11 &
1%
#3550
0%
