hardware/registers.v
module register_16bit(
    input clk,  // clock
    input rst,  // reset 
    input load, // load new value
    input o_en, // output enabled
    input [15:0] d, // data
    output [15:0] o // output
);
    reg [15:0] data_wire;

    // pipo register
    always @(posedge clk or posedge rst) begin
        if (rst) begin
            data_wire <= 16'h0000; // Clear the register value 
        end else if (load) begin
            data_wire <= d;
        end
    end

    // Tri-state buffer
    assign o = o_en ? data_wire : 16'hzzzz;
endmodule

tests/registers/register_tb.v
module register_tb();
    // -------------------------
    // Testbench Signals
    // -------------------------
    reg         clk;
    reg         rst;
    reg         R1_en;
    reg         R1_tri;      // separate tristate control
    reg  [15:0] counter;
    wire [15:0] output_bus;

    // -------------------------
    // DUT Instantiation
    // -------------------------
    register_16bit register(
        .clk   (clk),
        .rst   (rst),
        .load  (R1_en),
        .o_en  (R1_tri),     // driven independently
        .d     (counter),
        .o     (output_bus)
    );

    // -------------------------
    // Clock Generation: 10ns period
    // -------------------------
    initial clk = 0;
    always #5 clk = ~clk;

    // -------------------------
    // Task: Apply one clock cycle
    // -------------------------
    task tick;
        begin
            @(posedge clk);
            #1;
        end
    endtask

    // -------------------------
    // Task: Check output_bus value or hi-Z
    // -------------------------
    task check;
        input [15:0] expected;
        input        expect_hiz;
        input [63:0] test_num;
        begin
            if (expect_hiz) begin
                if (^output_bus === 1'bx)
                    $display("PASS [Test %0d] output_bus is Hi-Z as expected", test_num);
                else
                    $display("FAIL [Test %0d] expected Hi-Z, got %0h", test_num, output_bus);
            end else begin
                if (output_bus === expected)
                    $display("PASS [Test %0d] output_bus = %0h", test_num, output_bus);
                else
                    $display("FAIL [Test %0d] expected %0h, got %0h", test_num, expected, output_bus);
            end
        end
    endtask

    // -------------------------
    // Stimulus
    // -------------------------
    initial begin
        // Initialise
        rst     = 1;
        R1_en   = 0;
        R1_tri  = 0;
        counter = 16'h0000;

        // --------------------------------------------------
        // Test 1: Reset, both controls low -> Hi-Z
        // --------------------------------------------------
        tick; tick;
        check(16'hxxxx, 1, 1);

        // --------------------------------------------------
        // Test 2: Release reset, neither load nor o_en asserted
        // --------------------------------------------------
        rst = 0;
        tick;
        check(16'hxxxx, 1, 2);

        // --------------------------------------------------
        // Test 3: Load a value WITHOUT enabling the output
        // Register latches data, bus stays Hi-Z
        // --------------------------------------------------
        counter = 16'hA5A5;
        R1_en   = 1;
        tick;                   // latch A5A5
        R1_en   = 0;
        check(16'hxxxx, 1, 3); // o_en still low, bus should be Hi-Z

        // --------------------------------------------------
        // Test 4: Now enable the tristate output
        // Should see the loaded value on the bus
        // --------------------------------------------------
        R1_tri = 1;
        #2;
        check(16'hA5A5, 0, 4);

        // --------------------------------------------------
        // Test 5: Disable tristate -> bus goes Hi-Z again
        // --------------------------------------------------
        R1_tri = 0;
        #2;
        check(16'hxxxx, 1, 5);

        // --------------------------------------------------
        // Test 6: Load new value while output is disabled
        // --------------------------------------------------
        counter = 16'hDEAD;
        R1_en   = 1;
        tick;
        R1_en   = 0;
        check(16'hxxxx, 1, 6); // still Hi-Z

        // Enable output to verify new value was latched
        R1_tri = 1;
        #2;
        check(16'hDEAD, 0, 6);

        // --------------------------------------------------
        // Test 7: Load and output simultaneously
        // --------------------------------------------------
        counter = 16'hBEEF;
        R1_en   = 1;
        tick;
        R1_en   = 0;
        check(16'hBEEF, 0, 7); // R1_tri still high

        // --------------------------------------------------
        // Test 8: Assert reset while output enabled -> clears to 0
        // --------------------------------------------------
        rst = 1;
        tick;
        check(16'h0000, 0, 8);
        rst = 0;

        // --------------------------------------------------
        // Test 9: All 1s
        // --------------------------------------------------
        counter = 16'hFFFF;
        R1_en   = 1;
        tick;
        R1_en   = 0;
        check(16'hFFFF, 0, 9);

        // --------------------------------------------------
        // Test 10: Walking-ones pattern
        // --------------------------------------------------
        begin : walking_ones
            integer i;
            for (i = 0; i < 16; i = i + 1) begin
                counter = (16'h0001 << i);
                R1_en   = 1;
                tick;
                R1_en   = 0;
                if (output_bus === counter)
                    $display("PASS [Test 10.%0d] Walking-one bit %0d = %0h", i, i, output_bus);
                else
                    $display("FAIL [Test 10.%0d] expected %0h, got %0h", i, counter, output_bus);
            end
        end

        // --------------------------------------------------
        // Done
        // --------------------------------------------------
        R1_tri = 0;
        #20;
        $display("Testbench complete.");
        $finish;
    end

    // -------------------------
    // Waveform dump
    // -------------------------
    initial begin
        $dumpfile("register_tb.vcd");
        $dumpvars(0, register_tb);
    end
endmodule

register_tb.vcd
$date
	Wed May 13 13:24:05 2026
$end
$version
	Icarus Verilog
$end
$timescale
	1s
$end
$scope module register_tb $end
$var wire 16 ! output_bus [15:0] $end
$var reg 1 " R1_en $end
$var reg 1 # R1_tri $end
$var reg 1 $ clk $end
$var reg 16 % counter [15:0] $end
$var reg 1 & rst $end
$scope module register $end
$var wire 1 $ clk $end
$var wire 16 ' d [15:0] $end
$var wire 1 " load $end
$var wire 1 # o_en $end
$var wire 1 & rst $end
$var wire 16 ( o [15:0] $end
$var reg 16 ) data_wire [15:0] $end
$upscope $end
$scope begin walking_ones $end
$var integer 32 * i [31:0] $end
$upscope $end
$scope task check $end
$var reg 1 + expect_hiz $end
$var reg 16 , expected [15:0] $end
$var reg 64 - test_num [63:0] $end
$upscope $end
$scope task tick $end
$upscope $end
$upscope $end
$enddefinitions $end
$comment Show the parameter values. $end
$dumpall
$end
#0
$dumpvars
bx -
bx ,
x+
bx *
b0 )
bz (
b0 '
1&
b0 %
0$
0#
0"
bz !
$end
#5
1$
#10
0$
#15
1$
#16
0&
b1 -
1+
#20
0$
#25
1$
#26
1"
b1010010110100101 %
b1010010110100101 '
b10 -
#30
0$
#35
b1010010110100101 )
1$
#36
b1010010110100101 !
b1010010110100101 (
1#
b11 -
0"
#38
bz !
bz (
0#
b100 -
0+
b1010010110100101 ,
#40
1"
b1101111010101101 %
b1101111010101101 '
b101 -
1+
bx ,
0$
#45
b1101111010101101 )
1$
#46
b1101111010101101 !
b1101111010101101 (
1#
b110 -
0"
#48
1"
b1011111011101111 %
b1011111011101111 '
0+
b1101111010101101 ,
#50
0$
#55
b1011111011101111 !
b1011111011101111 (
b1011111011101111 )
1$
#56
b0 !
b0 (
b0 )
1&
b111 -
b1011111011101111 ,
0"
#60
0$
#65
1$
#66
1"
b1111111111111111 %
b1111111111111111 '
0&
b1000 -
b0 ,
#70
0$
#75
b1111111111111111 !
b1111111111111111 (
b1111111111111111 )
1$
#76
b1 %
b1 '
b0 *
b1001 -
b1111111111111111 ,
1"
#80
0$
#85
b1 !
b1 (
b1 )
1$
#86
b10 %
b10 '
b1 *
1"
#90
0$
#95
b10 !
b10 (
b10 )
1$
#96
b100 %
b100 '
b10 *
1"
#100
0$
#105
b100 !
b100 (
b100 )
1$
#106
b1000 %
b1000 '
b11 *
1"
#110
0$
#115
b1000 !
b1000 (
b1000 )
1$
#116
b10000 %
b10000 '
b100 *
1"
#120
0$
#125
b10000 !
b10000 (
b10000 )
1$
#126
b100000 %
b100000 '
b101 *
1"
#130
0$
#135
b100000 !
b100000 (
b100000 )
1$
#136
b1000000 %
b1000000 '
b110 *
1"
#140
0$
#145
b1000000 !
b1000000 (
b1000000 )
1$
#146
b10000000 %
b10000000 '
b111 *
1"
#150
0$
#155
b10000000 !
b10000000 (
b10000000 )
1$
#156
b100000000 %
b100000000 '
b1000 *
1"
#160
0$
#165
b100000000 !
b100000000 (
b100000000 )
1$
#166
b1000000000 %
b1000000000 '
b1001 *
1"
#170
0$
#175
b1000000000 !
b1000000000 (
b1000000000 )
1$
#176
b10000000000 %
b10000000000 '
b1010 *
1"
#180
0$
#185
b10000000000 !
b10000000000 (
b10000000000 )
1$
#186
b100000000000 %
b100000000000 '
b1011 *
1"
#190
0$
#195
b100000000000 !
b100000000000 (
b100000000000 )
1$
#196
b1000000000000 %
b1000000000000 '
b1100 *
1"
#200
0$
#205
b1000000000000 !
b1000000000000 (
b1000000000000 )
1$
#206
b10000000000000 %
b10000000000000 '
b1101 *
1"
#210
0$
#215
b10000000000000 !
b10000000000000 (
b10000000000000 )
1$
#216
b100000000000000 %
b100000000000000 '
b1110 *
1"
#220
0$
#225
b100000000000000 !
b100000000000000 (
b100000000000000 )
1$
#226
b1000000000000000 %
b1000000000000000 '
b1111 *
1"
#230
0$
#235
b1000000000000000 !
b1000000000000000 (
b1000000000000000 )
1$
#236
bz !
bz (
0#
b10000 *
0"
