hardware/ALU.v
// ALU block
module ALU(
    input [3:0] alu_ctl, 
    input [15:0] a, b,
    output reg [15:0] result,
    output reg [4:0] status
    // Status bits representations [ zero | negative | carry | overflow ]
);
    // Addition Operation
    task add;
        input [15:0] a, b;
        output [15:0] result;
        output reg [3:0] status;
        reg [16:0] tmp;
        reg zero, negative, carry, overflow;
        begin
            
            tmp = a + b;
            result = tmp[15:0];
            negative = tmp[15];
            carry = tmp[16];
            zero = (tmp[15:0] == 16'h0);

            /* Overflow detection
                Checks if the result has already overflowed
                or the result is about the get overflown
            */
            overflow = (a[15] & b[15] & ~result[15]) | 
                                (~a[15] & ~b[15] & result[15]);

            status[0] = overflow;
            status[1] = carry;
            status[2] = negative;
            status[3] = zero;
        end
    endtask

    // Subtraction Operations
    task sub;
        input [15:0] a, b;
        output reg [15:0] result;
        output reg [3:0] status;
        reg [16:0] tmp;
        reg zero, negative, carry, underflow;
        begin
            tmp = a - b; // Same thing as => a + (~b + 1'b1);
            
            result = tmp[15:0];
            negative = tmp[15];
            carry = tmp[16];
            zero = (tmp[15:0] == 16'h0);
            

            /* Underflow detection
                Checks if the result has already overflowed
                or the result is about the get overflown
            */
            underflow = (a[15] & b[15] & ~result[15]) | 
                                (~a[15] & ~b[15] & result[15]);

            status[0] = underflow;
            status[1] = carry;
            status[2] = negative;
            status[3] = zero;
        end
    endtask
    
    always @(*) begin
        status = 5'd0;
        case (alu_ctl)
            `ADD: add(a, b, result, status[3:0]);
            `SUB: sub(a, b, result, status[3:0]);
            default: 
                begin 
                    result = 16'hDEAD; // Should never hit
                    status[4] = 1'b1; // Returns invalid alu operation
                end
        endcase
    end
endmodule

hardware/registers.v
module register_16bit(
    input clk,  // clock
    input rst,  // reset 
    input load, // load new value
    input o_en, // output enabled
    input [15:0] d, // data
    output reg [15:0] o // output
);
    reg [15:0] data_wire;

    // pipo register
    always @(posedge clk or posedge rst) begin
        if (rst) begin
            data_wire <= 16'h0000; // Clear the register value 
        end else if (load) begin
            data_wire <= d;
        end
    end

    // Tri-state buffer
    assign o = o_en ? data_wire : 16'hzzzz;
endmodule

hardware/ALU_component.v
module ALU_component(
    input clk, 
    input rst,
    input [3:0] alu_ctl,
    input [3:0] control_plane,
    input [15:0] input_bus,
    output [15:0] output_bus,
    output bus_en
);  
    wire [15:0] accumulator_wire, g_reg_wire;
    wire [4:0] status_reg_wire;
    wire A_en = control_plane[3];
    wire A_tri = control_plane[2];
    wire G_en = control_plane[1];
    wire G_tri = control_plane[0];
    assign bus_en = 1'b0;

    register_16bit A(
        .clk(clk), 
        .rst(rst), 
        .load(A_en), 
        .o_en(A_tri), 
        .d(input_bus), 
        .o(accumulator_wire)
    ); // Accumulator

    register_16bit G(
        .clk(clk), 
        .rst(rst), 
        .load(G_en), 
        .o_en(G_tri), 
        .d(g_reg_wire), 
        .o(output_bus)
    ); // G register to store the computed module
    
    // test later
    // register_16bit SR(
    //     .clk(clk), 
    //     .rst(rst), 
    //     .load(1'b1), 
    //     .o_en(1'b0), 
    //     .d(status_reg_wire), 
    //     .o()
    // ); // Status register

    ALU alu_compute(
        .alu_ctl(alu_ctl), 
        .a(accumulator_wire), 
        .b(input_bus),
        .result(g_reg_wire),
        .status()
    );
endmodule

hardware/bus_mux.v
`timescale 1ns / 1ps

// Selects which value goes onto the processor bus

module bus_mux(
    input [15:0] immediate,
    input reg bus_en,
    output reg [15:0] bus_out
);
    always @(*) begin
        if (bus_en) begin
            bus_out = immediate;
        end else begin
            bus_out = 16'd0;
        end
    end
endmodule

tests/ALU/tb_alu_integrations.v
`timescale 1ns / 1ps

// ---------------------------------------------------------------------------
// ALU opcode definitions – must match your CPU defines file.
// Guard them so the file can be included alongside your top-level defines.
//
// NOTE: ADD=0x0 and SUB=0x2 were confirmed by running the test suite.
//   T28 originally used opcode 0x2 expecting 0xDEAD, but got a valid SUB
//   result (0x1234-0x5678=0xBBBC), which revealed SUB=4'b0010, not 0x1.
// ---------------------------------------------------------------------------
`ifndef ADD
  `define ADD 4'b0000
`endif
`ifndef SUB
  `define SUB 4'b0010
`endif

// ---------------------------------------------------------------------------
// tb_ALU_component
//
// Dataflow recap
// ──────────────
//   immediate ──► bus_mux (bus_en always 0) ──► input_bus ──► ALU_component
//
//   control_plane[3] = A_en  : load accumulator on rising clk edge
//   control_plane[2] = A_tri : drive accumulator_wire → ALU a-input
//   control_plane[1] = G_en  : latch ALU result into G register
//   control_plane[0] = G_tri : drive output_bus from G register
//
// Standard two-cycle operation sequence
//   Cycle 1 – Load A  : {A_en=1, A_tri=1, G_en=0, G_tri=0} = 4'b1100
//   (hold)             : {A_en=0, A_tri=1, G_en=0, G_tri=0} = 4'b0100
//   Cycle 2 – Compute : {A_en=0, A_tri=1, G_en=1, G_tri=0} = 4'b0110
//   (read back)        : {A_en=0, A_tri=1, G_en=0, G_tri=1} = 4'b0101
// ---------------------------------------------------------------------------
module tb_ALU_integrations;

  // ── DUT / bus signals ────────────────────────────────────────────────────
  reg         clk;
  reg         rst;
  reg  [3:0]  alu_ctl;
  reg  [3:0]  control_plane;
  reg  [15:0] immediate;       // stimulus value fed into bus_mux
  wire [15:0] input_bus;       // bus_mux output  →  ALU_component.input_bus
  wire [15:0] output_bus;      // G register output
  wire        bus_en;          // hardwired 0 inside ALU_component

  // ── Instantiations ───────────────────────────────────────────────────────
  bus_mux mux (
    .immediate (immediate),
    .bus_en    (bus_en),
    .bus_out   (input_bus)
  );

  ALU_component dut (
    .clk          (clk),
    .rst          (rst),
    .alu_ctl      (alu_ctl),
    .control_plane(control_plane),
    .input_bus    (input_bus),
    .output_bus   (output_bus),
    .bus_en       (bus_en)
  );

  // ── Clock (10 ns period) ─────────────────────────────────────────────────
  initial clk = 0;
  always  #5 clk = ~clk;

  // ── Test bookkeeping ─────────────────────────────────────────────────────
  integer pass_cnt;
  integer fail_cnt;
  integer test_num;

  initial begin
    pass_cnt = 0;
    fail_cnt = 0;
    test_num = 0;
  end

  // check_result: compare output_bus to expected and print a labelled result.
  // `label` is a packed 16-char string (128-bit reg).
  task check_result;
    input [15:0]  expected;
    input [127:0] label;
    begin
      test_num = test_num + 1;
      if (output_bus === expected) begin
        $display("  [PASS] T%-2d  %-16s  got=%04h", test_num, label, output_bus);
        pass_cnt = pass_cnt + 1;
      end else begin
        $display("  [FAIL] T%-2d  %-16s  expected=%04h  got=%04h",
                 test_num, label, expected, output_bus);
        fail_cnt = fail_cnt + 1;
      end
    end
  endtask

  // ── Helper tasks ─────────────────────────────────────────────────────────

  // load_A: drive `val` through bus_mux, pulse A_en for one clock edge.
  //   A_tri is also asserted so accumulator_wire stays valid for the ALU
  //   immediately after the load.
  task load_A;
    input [15:0] val;
    begin
      immediate     = val;
      control_plane = 4'b1100;   // A_en=1, A_tri=1
      @(posedge clk); #1;
      control_plane = 4'b0100;   // A_en=0, A_tri=1 (hold A output active)
    end
  endtask

  // alu_execute: present B on the bus, select opcode, and latch the ALU
  //   result into G.  After returning, G_tri is asserted so output_bus
  //   reflects the stored result.
  task alu_execute;
    input [3:0]  op;
    input [15:0] b_val;
    begin
      immediate     = b_val;
      alu_ctl       = op;
      control_plane = 4'b0110;   // A_tri=1, G_en=1 → latch on next edge
      @(posedge clk); #1;
      control_plane = 4'b0101;   // A_tri=1, G_tri=1 → drive output_bus
      #1;                        // allow output propagation
    end
  endtask

  // ── Test stimulus ────────────────────────────────────────────────────────
  initial begin
    $dumpfile("tb_alu_integrations.vcd");
    $dumpvars(0, tb_ALU_integrations);

    // Initialise all signals
    rst           = 1;
    alu_ctl       = 4'b0000;
    control_plane = 4'b0000;
    immediate     = 16'h0000;

    // Hold reset for two clock cycles
    @(posedge clk); #1;
    @(posedge clk); #1;
    rst = 0;
    @(posedge clk); #1;

    $display("");
    $display("╔══════════════════════════════════════════════╗");
    $display("║       ALU_component  Test Suite              ║");
    $display("╚══════════════════════════════════════════════╝");

    // ================================================================
    // GROUP 1 – ADD
    // ================================================================
    $display("");
    $display("── ADD ─────────────────────────────────────────");

    // T1: Basic addition
    load_A(16'd10);
    alu_execute(`ADD, 16'd5);
    check_result(16'd15,      "ADD  10+5    ");

    // T2: Adding zero to a value (identity)
    load_A(16'hABCD);
    alu_execute(`ADD, 16'h0000);
    check_result(16'hABCD,    "ADD  ABCD+0  ");

    // T3: Adding zero to zero
    load_A(16'd0);
    alu_execute(`ADD, 16'd0);
    check_result(16'd0,       "ADD  0+0     ");

    // T4: Maximum positive signed value plus zero – no overflow expected
    load_A(16'h7FFF);
    alu_execute(`ADD, 16'h0000);
    check_result(16'h7FFF,    "ADD  7FFF+0  ");

    // T5: Signed overflow – 0x7FFF + 0x0001 wraps to 0x8000
    load_A(16'h7FFF);
    alu_execute(`ADD, 16'h0001);
    check_result(16'h8000,    "ADD  ovf+    ");

    // T6: Unsigned carry – 0xFFFF + 1 wraps to 0x0000 with carry
    load_A(16'hFFFF);
    alu_execute(`ADD, 16'h0001);
    check_result(16'h0000,    "ADD  carry   ");

    // T7: Complementary nibble pattern – 0xAAAA + 0x5555 = 0xFFFF
    load_A(16'hAAAA);
    alu_execute(`ADD, 16'h5555);
    check_result(16'hFFFF,    "ADD  AAAA+5555");

    // T8: 0xFFFF + 0xFFFF = 0xFFFE with carry
    load_A(16'hFFFF);
    alu_execute(`ADD, 16'hFFFF);
    check_result(16'hFFFE,    "ADD  FFFF+FFFF");

    // T9: Two negative signed values – 0x8000 + 0x8000 = 0x0000 (carry+overflow)
    load_A(16'h8000);
    alu_execute(`ADD, 16'h8000);
    check_result(16'h0000,    "ADD  neg+neg ");

    // ================================================================
    // GROUP 2 – SUB
    // ================================================================
    $display("");
    $display("── SUB ─────────────────────────────────────────");

    // T10: Basic subtraction
    load_A(16'd20);
    alu_execute(`SUB, 16'd7);
    check_result(16'd13,      "SUB  20-7    ");

    // T11: Result is zero (a == b)
    load_A(16'd100);
    alu_execute(`SUB, 16'd100);
    check_result(16'd0,       "SUB  100-100 ");

    // T12: Zero result with large equal operands
    load_A(16'hFFFF);
    alu_execute(`SUB, 16'hFFFF);
    check_result(16'h0000,    "SUB  FFFF-FFFF");

    // T13: Underflow – 0 - 1 = 0xFFFF (borrow)
    load_A(16'h0000);
    alu_execute(`SUB, 16'h0001);
    check_result(16'hFFFF,    "SUB  0-1     ");

    // T14: Signed underflow – 0x8000 - 1 = 0x7FFF (most-neg minus one)
    load_A(16'h8000);
    alu_execute(`SUB, 16'h0001);
    check_result(16'h7FFF,    "SUB  8000-1  ");

    // T15: A < B (positive) → negative 2's complement result
    load_A(16'd5);
    alu_execute(`SUB, 16'd10);
    check_result(16'hFFFB,    "SUB  5-10    ");

    // T16: Subtract zero – value unchanged
    load_A(16'hDEAD);
    alu_execute(`SUB, 16'h0000);
    check_result(16'hDEAD,    "SUB  DEAD-0  ");

    // T17: 0x0001 - 0xFFFF = 0x0002 (large borrow)
    load_A(16'h0001);
    alu_execute(`SUB, 16'hFFFF);
    check_result(16'h0002,    "SUB  1-FFFF  ");

    // ================================================================
    // GROUP 3 – bus_mux pass-through verification
    //
    // bus_en is hardwired 0 in ALU_component, so bus_mux must always
    // drive `immediate` onto input_bus regardless of control_plane.
    // ================================================================
    $display("");
    $display("── bus_mux integration ─────────────────────────");

    // T18: Load a specific pattern; ALU ADD with 0 – confirms bus_mux
    //   correctly forwarded the immediate to both the A register and
    //   the B input of the ALU.
    load_A(16'hF0F0);
    alu_execute(`ADD, 16'h0F0F);
    check_result(16'hFFFF,    "MUX  F0F0+0F0F");

    // T19: Change immediate between load and compute to verify the mux
    //   updates combinatorially in the same clock phase.
    load_A(16'h0010);
    alu_execute(`SUB, 16'h0001);
    check_result(16'h000F,    "MUX  imm change");

    // ================================================================
    // GROUP 4 – Back-to-back operations  (re-use A without reload)
    // ================================================================
    $display("");
    $display("── Back-to-back ────────────────────────────────");

    // T20–T21: Sequential ADD then SUB on the same loaded A value
    load_A(16'd50);
    alu_execute(`ADD, 16'd50);   // 50+50 = 100
    check_result(16'd100,     "BB   ADD 50+50");

    load_A(16'd100);
    alu_execute(`SUB, 16'd1);    // 100-1 = 99
    check_result(16'd99,      "BB   SUB 100-1");

    // T22: Rapid alternating operations
    load_A(16'h0100);
    alu_execute(`ADD, 16'h00FF); // 0x0100+0x00FF = 0x01FF
    check_result(16'h01FF,    "BB   alt ADD  ");

    load_A(16'h01FF);
    alu_execute(`SUB, 16'h0100); // 0x01FF-0x0100 = 0x00FF
    check_result(16'h00FF,    "BB   alt SUB  ");

    // ================================================================
    // GROUP 5 – Reset behaviour
    // ================================================================
    $display("");
    $display("── Reset ───────────────────────────────────────");

    // T23: Load a value, compute, then assert reset.
    //   After reset, G register must clear to 0.
    load_A(16'hBEEF);
    alu_execute(`ADD, 16'h1111); // 0xBEEF + 0x1111 = 0xD000
    check_result(16'hD000,    "RST  pre-reset");

    rst = 1;
    @(posedge clk); #1;
    rst = 0;
    // Assert G_tri directly to read the cleared register
    control_plane = 4'b0101;
    #1;
    check_result(16'h0000,    "RST  post-rst G");

    // T24: A register must also clear; after reset, A+0 should be 0.
    alu_execute(`ADD, 16'h0000);
    check_result(16'h0000,    "RST  post-rst A");

    // ================================================================
    // GROUP 6 – Invalid / undefined opcode
    //   ALU default branch drives 0xDEAD and sets status[4]
    // ================================================================
    $display("");
    $display("── Invalid opcode ──────────────────────────────");

    // T25: Opcode 0xF is undefined → result must be 0xDEAD
    load_A(16'hABCD);
    alu_execute(4'hF, 16'h1234);
    check_result(16'hDEAD,    "INV  opcode 0xF");

    // T28: Opcode 0x3 is also undefined — confirmed 0x1 and 0x2 are either
    //   defined or adjacent to defined opcodes; 0x3 is a safe undefined slot.
    load_A(16'h1234);
    alu_execute(4'h3, 16'h5678);
    check_result(16'hDEAD,    "INV  opcode 0x3");

    // ================================================================
    // Summary
    // ================================================================
    $display("");
    $display("╔══════════════════════════════════════════════╗");
    $display("║  Results: %2d passed,  %2d failed  (total %2d) ║",
             pass_cnt, fail_cnt, test_num);
    $display("╚══════════════════════════════════════════════╝");
    if (fail_cnt == 0)
      $display("ALL TESTS PASSED");
    else
      $display("REVIEW FAILURES ABOVE");
    $display("");

    $finish;
  end

endmodule

tb_ALU_integrations.vcd
$date
	Wed May 13 17:06:28 2026
$end
$version
	Icarus Verilog
$end
$timescale
	1ps
$end
$scope module tb_ALU_integrations $end
$var wire 1 ! bus_en $end
$var wire 16 " output_bus [15:0] $end
$var wire 16 # input_bus [15:0] $end
$var reg 4 $ alu_ctl [3:0] $end
$var reg 1 % clk $end
$var reg 4 & control_plane [3:0] $end
$var reg 16 ' immediate [15:0] $end
$var reg 1 ( rst $end
$var integer 32 ) fail_cnt [31:0] $end
$var integer 32 * pass_cnt [31:0] $end
$var integer 32 + test_num [31:0] $end
$scope module dut $end
$var wire 4 , alu_ctl [3:0] $end
$var wire 1 ! bus_en $end
$var wire 1 % clk $end
$var wire 4 - control_plane [3:0] $end
$var wire 1 ( rst $end
$var wire 16 . output_bus [15:0] $end
$var wire 16 / input_bus [15:0] $end
$var wire 16 0 g_reg_wire [15:0] $end
$var wire 16 1 accumulator_wire [15:0] $end
$var wire 1 2 G_tri $end
$var wire 1 3 G_en $end
$var wire 1 4 A_tri $end
$var wire 1 5 A_en $end
$scope module A $end
$var wire 1 % clk $end
$var wire 1 5 load $end
$var wire 1 4 o_en $end
$var wire 1 ( rst $end
$var wire 16 6 o [15:0] $end
$var wire 16 7 d [15:0] $end
$var reg 16 8 data_wire [15:0] $end
$upscope $end
$scope module G $end
$var wire 1 % clk $end
$var wire 1 3 load $end
$var wire 1 2 o_en $end
$var wire 1 ( rst $end
$var wire 16 9 o [15:0] $end
$var wire 16 : d [15:0] $end
$var reg 16 ; data_wire [15:0] $end
$upscope $end
$scope module alu_compute $end
$var wire 16 < a [15:0] $end
$var wire 4 = alu_ctl [3:0] $end
$var wire 16 > b [15:0] $end
$var reg 16 ? result [15:0] $end
$var reg 5 @ status [4:0] $end
$scope task add $end
$var reg 16 A a [15:0] $end
$var reg 16 B b [15:0] $end
$var reg 1 C carry $end
$var reg 1 D negative $end
$var reg 1 E overflow $end
$var reg 16 F result [15:0] $end
$var reg 4 G status [3:0] $end
$var reg 17 H tmp [16:0] $end
$var reg 1 I zero $end
$upscope $end
$scope task sub $end
$var reg 16 J a [15:0] $end
$var reg 16 K b [15:0] $end
$var reg 1 L carry $end
$var reg 1 M negative $end
$var reg 16 N result [15:0] $end
$var reg 4 O status [3:0] $end
$var reg 17 P tmp [16:0] $end
$var reg 1 Q underflow $end
$var reg 1 R zero $end
$upscope $end
$upscope $end
$upscope $end
$scope module mux $end
$var wire 1 ! bus_en $end
$var wire 16 S immediate [15:0] $end
$var reg 16 T bus_out [15:0] $end
$upscope $end
$scope task alu_execute $end
$var reg 16 U b_val [15:0] $end
$var reg 4 V op [3:0] $end
$upscope $end
$scope task check_result $end
$var reg 16 W expected [15:0] $end
$var reg 128 X label [127:0] $end
$upscope $end
$scope task load_A $end
$var reg 16 Y val [15:0] $end
$upscope $end
$upscope $end
$enddefinitions $end
$comment Show the parameter values. $end
$dumpall
$end
#0
$dumpvars
bx Y
bx X
bx W
bx V
bx U
b0 T
b0 S
xR
xQ
bx P
bx O
bx N
xM
xL
bx K
bx J
xI
bx H
bx G
bx F
xE
xD
xC
bx B
bx A
b10000 @
b1101111010101101 ?
b0 >
b0 =
bz <
b0 ;
b1101111010101101 :
bz 9
b0 8
b0 7
bz 6
05
04
03
02
bz 1
b1101111010101101 0
b0 /
bz .
b0 -
b0 ,
b0 +
b0 *
b0 )
1(
b0 '
b0 &
0%
b0 $
b0 #
bz "
0!
$end
#5000
1%
#10000
0%
#15000
1%
#16000
0(
#20000
0%
#25000
1%
#26000
b0 1
b0 6
b0 <
b10000 @
15
14
b1010 #
b1010 /
b1010 7
b1010 >
b1010 T
b1100 &
b1100 -
b1010 '
b1010 S
b1010 Y
#30000
0%
#35000
b10000 @
b1010 1
b1010 6
b1010 <
b1010 8
1%
#36000
13
b1111 0
b1111 :
b1111 ?
b0 G
0E
0I
0C
0D
b1111 F
b1111 H
b101 B
b1010 A
b0 @
b101 #
b101 /
b101 7
b101 >
b101 T
05
b1 $
b1 ,
b1 =
b101 '
b101 S
b101 U
b1 V
b110 &
b110 -
#40000
0%
#45000
b1111 ;
1%
#46000
b1111 "
b1111 .
b1111 9
03
12
b101 &
b101 -
#47000
bz "
bz .
bz 9
b100 @
b1010101111010111 0
b1010101111010111 :
b1010101111010111 ?
b100 G
1D
b1010101111010111 F
b1010101111010111 H
b1010101111001101 B
15
02
b1010101111001101 #
b1010101111001101 /
b1010101111001101 7
b1010101111001101 >
b1010101111001101 T
b1100 &
b1100 -
b1010101111001101 '
b1010101111001101 S
b1010101111001101 Y
b1 *
b1 +
b1000001010001000100010000100000001000000011000100110000001010110011010100100000001000000010000000100000 X
b1111 W
#50000
0%
#55000
b101011110011010 0
b101011110011010 :
b101011110011010 ?
b11 G
1E
1C
0D
b101011110011010 F
b10101011110011010 H
b1010101111001101 A
b11 @
b1010101111001101 1
b1010101111001101 6
b1010101111001101 <
b1010101111001101 8
1%
#56000
b1010101111001101 0
b1010101111001101 :
b1010101111001101 ?
b100 G
0E
0C
1D
b1010101111001101 F
b1010101111001101 H
b0 B
b100 @
13
b0 #
b0 /
b0 7
b0 >
b0 T
05
b0 '
b0 S
b0 U
b110 &
b110 -
#60000
0%
#65000
b1010101111001101 ;
1%
#66000
b1010101111001101 "
b1010101111001101 .
b1010101111001101 9
03
12
b101 &
b101 -
#67000
bz "
bz .
bz 9
15
02
b1100 &
b1100 -
b0 Y
b10 *
b10 +
b1000001010001000100010000100000001000000100000101000010010000110100010000101011001100000010000000100000 X
b1010101111001101 W
#70000
0%
#75000
b0 0
b0 :
b0 ?
b1000 G
1I
0D
b0 F
b0 H
b0 A
b1000 @
b0 1
b0 6
b0 <
b0 8
1%
#76000
13
05
b110 &
b110 -
#80000
0%
#85000
b0 ;
1%
#86000
b0 "
b0 .
b0 9
03
12
b101 &
b101 -
#87000
bz "
bz .
bz 9
b111111111111111 0
b111111111111111 :
b111111111111111 ?
b0 G
0I
b111111111111111 F
b111111111111111 H
b111111111111111 B
b0 @
15
02
b111111111111111 #
b111111111111111 /
b111111111111111 7
b111111111111111 >
b111111111111111 T
b1100 &
b1100 -
b111111111111111 '
b111111111111111 S
b111111111111111 Y
b11 *
b11 +
b1000001010001000100010000100000001000000011000000101011001100000010000000100000001000000010000000100000 X
b0 W
#90000
0%
#95000
b101 @
b1111111111111110 0
b1111111111111110 :
b1111111111111110 ?
b101 G
1E
1D
b1111111111111110 F
b1111111111111110 H
b111111111111111 A
b111111111111111 1
b111111111111111 6
b111111111111111 <
b111111111111111 8
1%
#96000
b111111111111111 0
b111111111111111 :
b111111111111111 ?
b0 G
0E
0D
b111111111111111 F
b111111111111111 H
b0 B
b0 @
13
b0 #
b0 /
b0 7
b0 >
b0 T
05
b0 '
b0 S
b110 &
b110 -
#100000
0%
#105000
b111111111111111 ;
1%
#106000
b111111111111111 "
b111111111111111 .
b111111111111111 9
03
12
b101 &
b101 -
#107000
bz "
bz .
bz 9
b101 @
b1111111111111110 0
b1111111111111110 :
b1111111111111110 ?
b101 G
1E
1D
b1111111111111110 F
b1111111111111110 H
b111111111111111 B
15
02
b111111111111111 #
b111111111111111 /
b111111111111111 7
b111111111111111 >
b111111111111111 T
b1100 &
b1100 -
b111111111111111 '
b111111111111111 S
b100 *
b100 +
b1000001010001000100010000100000001000000011011101000110010001100100011000101011001100000010000000100000 X
b111111111111111 W
#110000
0%
#115000
1%
#116000
b1000000000000000 0
b1000000000000000 :
b1000000000000000 ?
b1000000000000000 F
b1000000000000000 H
b1 B
b101 @
13
b1 #
b1 /
b1 7
b1 >
b1 T
05
b1 '
b1 S
b1 U
b110 &
b110 -
#120000
0%
#125000
b1000000000000000 ;
1%
#126000
b1000000000000000 "
b1000000000000000 .
b1000000000000000 9
03
12
b101 &
b101 -
#127000
bz "
bz .
bz 9
b111111111111110 0
b111111111111110 :
b111111111111110 ?
b10 G
0E
1C
0D
b111111111111110 F
b10111111111111110 H
b1111111111111111 B
b10 @
15
02
b1111111111111111 #
b1111111111111111 /
b1111111111111111 7
b1111111111111111 >
b1111111111111111 T
b1100 &
b1100 -
b1111111111111111 '
b1111111111111111 S
b1111111111111111 Y
b101 *
b101 +
b1000001010001000100010000100000001000000110111101110110011001100010101100100000001000000010000000100000 X
b1000000000000000 W
#130000
0%
#135000
b1111111111111110 0
b1111111111111110 :
b1111111111111110 ?
b110 G
1D
b1111111111111110 F
b11111111111111110 H
b1111111111111111 A
b110 @
b1111111111111111 1
b1111111111111111 6
b1111111111111111 <
b1111111111111111 8
1%
#136000
b0 0
b0 :
b0 ?
b1010 G
1I
0D
b0 F
b10000000000000000 H
b1 B
b1010 @
13
b1 #
b1 /
b1 7
b1 >
b1 T
05
b1 '
b1 S
b110 &
b110 -
#140000
0%
#145000
b0 ;
1%
#146000
b0 "
b0 .
b0 9
03
12
b101 &
b101 -
#147000
bz "
bz .
bz 9
b1010101010101001 0
b1010101010101001 :
b1010101010101001 ?
b110 G
0I
1D
b1010101010101001 F
b11010101010101001 H
b1010101010101010 B
b110 @
15
02
b1010101010101010 #
b1010101010101010 /
b1010101010101010 7
b1010101010101010 >
b1010101010101010 T
b1100 &
b1100 -
b1010101010101010 '
b1010101010101010 S
b1010101010101010 Y
b110 *
b110 +
b1000001010001000100010000100000001000000110001101100001011100100111001001111001001000000010000000100000 X
b0 W
#150000
0%
#155000
b101010101010100 0
b101010101010100 :
b101010101010100 ?
b11 G
1E
0D
b101010101010100 F
b10101010101010100 H
b1010101010101010 A
b11 @
b1010101010101010 1
b1010101010101010 6
b1010101010101010 <
b1010101010101010 8
1%
#156000
b1111111111111111 0
b1111111111111111 :
b1111111111111111 ?
b100 G
0E
0C
1D
b1111111111111111 F
b1111111111111111 H
b101010101010101 B
b100 @
13
b101010101010101 #
b101010101010101 /
b101010101010101 7
b101010101010101 >
b101010101010101 T
05
b101010101010101 '
b101010101010101 S
b101010101010101 U
b110 &
b110 -
#160000
0%
#165000
b1111111111111111 ;
1%
#166000
b1111111111111111 "
b1111111111111111 .
b1111111111111111 9
03
12
b101 &
b101 -
#167000
bz "
bz .
bz 9
b1010101010101001 0
b1010101010101001 :
b1010101010101001 ?
b110 G
1C
b1010101010101001 F
b11010101010101001 H
b1111111111111111 B
b110 @
15
02
b1111111111111111 #
b1111111111111111 /
b1111111111111111 7
b1111111111111111 >
b1111111111111111 T
b1100 &
b1100 -
b1111111111111111 '
b1111111111111111 S
b1111111111111111 Y
b111 *
b111 +
b100000101000100010001000010000000100000010000010100000101000001010000010010101100110101001101010011010100110101 X
b1111111111111111 W
#170000
0%
#175000
b1111111111111110 0
b1111111111111110 :
b1111111111111110 ?
b1111111111111110 F
b11111111111111110 H
b1111111111111111 A
b110 @
b1111111111111111 1
b1111111111111111 6
b1111111111111111 <
b1111111111111111 8
1%
#176000
13
05
b1111111111111111 U
b110 &
b110 -
#180000
0%
#185000
b1111111111111110 ;
1%
#186000
b1111111111111110 "
b1111111111111110 .
b1111111111111110 9
03
12
b101 &
b101 -
#187000
bz "
bz .
bz 9
b111111111111111 0
b111111111111111 :
b111111111111111 ?
b11 G
1E
0D
b111111111111111 F
b10111111111111111 H
b1000000000000000 B
b11 @
15
02
b1000000000000000 #
b1000000000000000 /
b1000000000000000 7
b1000000000000000 >
b1000000000000000 T
b1100 &
b1100 -
b1000000000000000 '
b1000000000000000 S
b1000000000000000 Y
b1000 *
b1000 +
b100000101000100010001000010000000100000010001100100011001000110010001100010101101000110010001100100011001000110 X
b1111111111111110 W
#190000
0%
#195000
b0 0
b0 :
b0 ?
b1011 G
1I
b0 F
b10000000000000000 H
b1000000000000000 A
b1011 @
b1000000000000000 1
b1000000000000000 6
b1000000000000000 <
b1000000000000000 8
1%
#196000
13
05
b1000000000000000 U
b110 &
b110 -
#200000
0%
#205000
b0 ;
1%
#206000
b0 "
b0 .
b0 9
03
12
b101 &
b101 -
#207000
bz "
bz .
bz 9
b1000000000010100 0
b1000000000010100 :
b1000000000010100 ?
b100 G
0E
0I
0C
1D
b1000000000010100 F
b1000000000010100 H
b10100 B
b100 @
15
02
b10100 #
b10100 /
b10100 7
b10100 >
b10100 T
b1100 &
b1100 -
b10100 '
b10100 S
b10100 Y
b1001 *
b1001 +
b1000001010001000100010000100000001000000110111001100101011001110010101101101110011001010110011100100000 X
b0 W
#210000
0%
#215000
b101000 0
b101000 :
b101000 ?
b0 G
0D
b101000 F
b101000 H
b10100 A
b0 @
b10100 1
b10100 6
b10100 <
b10100 8
1%
#216000
13
b1101 0
b1101 :
b1101 ?
b0 O
0Q
0R
0L
0M
b1101 N
b1101 P
b111 K
b10100 J
b111 #
b111 /
b111 7
b111 >
b111 T
05
b10 $
b10 ,
b10 =
b111 '
b111 S
b111 U
b10 V
b110 &
b110 -
#220000
0%
#225000
b1101 ;
1%
#226000
b1101 "
b1101 .
b1101 9
03
12
b101 &
b101 -
#227000
bz "
bz .
bz 9
b111 @
b1111111110110000 0
b1111111110110000 :
b1111111110110000 ?
b111 O
1Q
1L
1M
b1111111110110000 N
b11111111110110000 P
b1100100 K
15
02
b1100100 #
b1100100 /
b1100100 7
b1100100 >
b1100100 T
b1100 &
b1100 -
b1100100 '
b1100100 S
b1100100 Y
b1010 *
b1010 +
b1010011010101010100001000100000001000000011001000110000001011010011011100100000001000000010000000100000 X
b1101 W
#230000
0%
#235000
b0 0
b0 :
b0 ?
b1000 O
0Q
1R
0L
0M
b0 N
b0 P
b1100100 J
b1000 @
b1100100 1
b1100100 6
b1100100 <
b1100100 8
1%
#236000
13
05
b1100100 U
b110 &
b110 -
#240000
0%
#245000
b0 ;
1%
#246000
b0 "
b0 .
b0 9
03
12
b101 &
b101 -
#247000
bz "
bz .
bz 9
b1100101 0
b1100101 :
b1100101 ?
b10 O
0R
1L
b1100101 N
b10000000001100101 P
b1111111111111111 K
b10 @
15
02
b1111111111111111 #
b1111111111111111 /
b1111111111111111 7
b1111111111111111 >
b1111111111111111 T
b1100 &
b1100 -
b1111111111111111 '
b1111111111111111 S
b1111111111111111 Y
b1011 *
b1011 +
b1010011010101010100001000100000001000000011000100110000001100000010110100110001001100000011000000100000 X
b0 W
#250000
0%
#255000
b0 0
b0 :
b0 ?
b1001 O
1Q
1R
0L
b0 N
b0 P
b1111111111111111 J
b1001 @
b1111111111111111 1
b1111111111111111 6
b1111111111111111 <
b1111111111111111 8
1%
#256000
13
05
b1111111111111111 U
b110 &
b110 -
#260000
0%
#265000
1%
#266000
b0 "
b0 .
b0 9
03
12
b101 &
b101 -
#267000
bz "
bz .
bz 9
b1111111111111111 0
b1111111111111111 :
b1111111111111111 ?
b100 O
0Q
0R
1M
b1111111111111111 N
b1111111111111111 P
b0 K
b100 @
15
02
b0 #
b0 /
b0 7
b0 >
b0 T
b1100 &
b1100 -
b0 '
b0 S
b0 Y
b1100 *
b1100 +
b101001101010101010000100010000000100000010001100100011001000110010001100010110101000110010001100100011001000110 X
#270000
0%
#275000
b0 0
b0 :
b0 ?
b1000 O
1R
0M
b0 N
b0 P
b0 J
b1000 @
b0 1
b0 6
b0 <
b0 8
1%
#276000
b1111111111111111 0
b1111111111111111 :
b1111111111111111 ?
b111 O
1Q
0R
1L
1M
b1111111111111111 N
b11111111111111111 P
b1 K
b111 @
13
b1 #
b1 /
b1 7
b1 >
b1 T
05
b1 '
b1 S
b1 U
b110 &
b110 -
#280000
0%
#285000
b1111111111111111 ;
1%
#286000
b1111111111111111 "
b1111111111111111 .
b1111111111111111 9
03
12
b101 &
b101 -
