hardware/bus_mux.v
`timescale 1ns / 1ps

module bus_mux(
    input  [15:0] immediate,
    input         bus_en,
    output reg [15:0] bus_out
);
    always @(*) begin
        if (bus_en) begin
            bus_out = 16'bz;        // register is driving — release the bus
        end else begin
            bus_out = immediate;    // no register active — drive immediate
        end
    end
endmodule

hardware/registers.v
module register_16bit(
    input clk,  // clock
    input rst,  // reset 
    input load, // load new value
    input o_en, // output enabled
    input [15:0] d, // data
    output reg [15:0] o // output
);
    reg [15:0] data_wire;

    // pipo register
    always @(posedge clk or posedge rst) begin
        if (rst) begin
            data_wire <= 16'h0000; // Clear the register value 
        end else if (load) begin
            data_wire <= d;
        end
    end

    // Tri-state buffer
    assign o = o_en ? data_wire : 16'hzzzz;
endmodule

hardware/register_file.v
module register_file(
    input clk,
    input rst,
    input wire [5:0] control_plane,
    input [15:0] input_bus,
    output [15:0] output_bus, 
    output bus_en
);
    
    wire R1_en = control_plane[5];
    wire R1_tri = control_plane[4]; 
    wire R2_en = control_plane[3]; 
    wire R2_tri = control_plane[2]; 
    wire R3_en = control_plane[1]; 
    wire R3_tri = control_plane[0];

    assign bus_en = R1_tri | R2_tri | R3_tri;

    register_16bit R1 (
        .clk(clk), 
        .rst(rst), 
        .load(R1_en), 
        .o_en(R1_tri), 
        .d(input_bus), 
        .o(output_bus));

    register_16bit R2 (
        .clk(clk), 
        .rst(rst), 
        .load(R2_en), 
        .o_en(R2_tri), 
        .d(input_bus), 
        .o(output_bus));

    register_16bit R3 (
        .clk(clk), 
        .rst(rst), 
        .load(R3_en), 
        .o_en(R3_tri), 
        .d(input_bus), 
        .o(output_bus));

endmodule

tests/registers/tb_integration.v
`timescale 1ns / 1ps

module tb_integration;

    // -------------------------
    // Testbench Signals
    // -------------------------
    reg         clk;
    reg         rst;
    reg  [5:0]  control_plane;
    reg  [15:0] immediate;

    wire [15:0] shared_bus;
    wire        bus_en;        // ← now driven by register_file output

    // -------------------------
    // DUT Instantiations
    // -------------------------
    register_file rf (
        .clk           (clk),
        .rst           (rst),
        .control_plane (control_plane),
        .input_bus     (shared_bus),
        .output_bus    (shared_bus),
        .bus_en        (bus_en)       // ← register file tells mux when to release
    );

    bus_mux mux (
        .immediate (immediate),
        .bus_en    (bus_en),           // ← wired directly from register_file
        .bus_out   (shared_bus)
    );

    // -------------------------
    // Control plane aliases
    // -------------------------
    localparam R1_LOAD = 6'b100000;
    localparam R1_OUT  = 6'b010000;
    localparam R2_LOAD = 6'b001000;
    localparam R2_OUT  = 6'b000100;
    localparam R3_LOAD = 6'b000010;
    localparam R3_OUT  = 6'b000001;

    // -------------------------
    // Clock
    // -------------------------
    initial clk = 0;
    always #5 clk = ~clk;

    task tick;
        begin
            @(posedge clk);
            #1;
        end
    endtask

    task check;
        input [15:0] expected;
        input        expect_hiz;
        input [63:0] test_num;
        begin
            if (expect_hiz) begin
                if (^shared_bus === 1'bx)
                    $display("PASS [Test %0d] shared_bus is Hi-Z", test_num);
                else
                    $display("FAIL [Test %0d] expected Hi-Z, got %0h", test_num, shared_bus);
            end else begin
                if (shared_bus === expected)
                    $display("PASS [Test %0d] shared_bus = %0h", test_num, shared_bus);
                else
                    $display("FAIL [Test %0d] expected %0h, got %0h", test_num, expected, shared_bus);
            end
        end
    endtask

    // -------------------------
    // Stimulus
    // -------------------------
    initial begin
        rst           = 1;
        immediate     = 16'h0000;
        control_plane = 6'b000000;
        // Note: bus_en is no longer set here — it's automatic from register_file

        // --------------------------------------------------
        // Test 1: Reset — all registers cleared
        // bus_en=0 so mux drives Hi-Z, registers drive 0 via tristate
        // --------------------------------------------------
        $display("--- Test 1: Reset ---");
        tick; tick;
        rst = 0;
        control_plane = R1_OUT; #2; check(16'h0000, 0, 1); control_plane = 6'b0; #2;
        control_plane = R2_OUT; #2; check(16'h0000, 0, 1); control_plane = 6'b0; #2;
        control_plane = R3_OUT; #2; check(16'h0000, 0, 1); control_plane = 6'b0; #2;

        // --------------------------------------------------
        // Test 2: Load 0xAAAA into R1
        // bus_en goes LOW (no tri active), mux drives immediate onto shared_bus
        // --------------------------------------------------
        $display("--- Test 2: Load 0xAAAA into R1 ---");
        immediate     = 16'hAAAA;
        control_plane = R1_LOAD;  // bus_en=0 automatically, mux drives immediate
        tick;
        control_plane = 6'b000000;

        // --------------------------------------------------
        // Test 3: Read R1
        // --------------------------------------------------
        $display("--- Test 3: Read R1 (expect 0xAAAA) ---");
        control_plane = R1_OUT;   // bus_en=1 automatically, mux goes Hi-Z
        #2;
        check(16'hAAAA, 0, 3);
        control_plane = 6'b000000;

        // --------------------------------------------------
        // Test 4: Load 0x1234 into R2
        // --------------------------------------------------
        $display("--- Test 4: Load 0x1234 into R2 ---");
        immediate     = 16'h1234;
        control_plane = R2_LOAD;
        tick;
        control_plane = 6'b000000;

        // --------------------------------------------------
        // Test 5: Read R2
        // --------------------------------------------------
        $display("--- Test 5: Read R2 (expect 0x1234) ---");
        control_plane = R2_OUT;
        #2;
        check(16'h1234, 0, 5);
        control_plane = 6'b000000;

        // --------------------------------------------------
        // Test 6: Load 0x5678 into R3
        // --------------------------------------------------
        $display("--- Test 6: Load 0x5678 into R3 ---");
        immediate     = 16'h5678;
        control_plane = R3_LOAD;
        tick;
        control_plane = 6'b000000;

        // --------------------------------------------------
        // Test 7: Read R3
        // --------------------------------------------------
        $display("--- Test 7: Read R3 (expect 0x5678) ---");
        control_plane = R3_OUT;
        #2;
        check(16'h5678, 0, 7);
        control_plane = 6'b000000;

        // --------------------------------------------------
        // Test 8: Register-to-register transfer R1 -> R2
        // R1_tri=1 so bus_en=1, mux releases, R1 drives bus, R2 latches
        // --------------------------------------------------
        $display("--- Test 8: R1 -> R2 transfer ---");
        immediate = 16'hAAAA; control_plane = R1_LOAD; tick;
        control_plane = 6'b000000; #2;
        control_plane = R1_OUT | R2_LOAD; // bus_en auto-high, mux releases
        tick;
        control_plane = 6'b000000; #2;
        control_plane = R2_OUT; #2; check(16'hAAAA, 0, 8); control_plane = 6'b0; #2;
        control_plane = R1_OUT; #2; check(16'hAAAA, 0, 8); control_plane = 6'b0;

        // --------------------------------------------------
        // Test 9: Broadcast immediate to all registers
        // --------------------------------------------------
        $display("--- Test 9: Broadcast 0xBEEF to all registers ---");
        immediate     = 16'hBEEF;
        control_plane = R1_LOAD | R2_LOAD | R3_LOAD; // bus_en=0, mux drives
        tick;
        control_plane = 6'b000000; #2;
        control_plane = R1_OUT; #2; check(16'hBEEF, 0, 9); control_plane = 6'b0; #2;
        control_plane = R2_OUT; #2; check(16'hBEEF, 0, 9); control_plane = 6'b0; #2;
        control_plane = R3_OUT; #2; check(16'hBEEF, 0, 9); control_plane = 6'b0;

        // --------------------------------------------------
        // Test 10: Mid-operation reset
        // --------------------------------------------------
        $display("--- Test 10: Mid-operation reset ---");
        immediate = 16'hDEAD; control_plane = R1_LOAD | R2_LOAD; tick;
        control_plane = 6'b000000;
        rst = 1; tick; rst = 0;
        control_plane = R1_OUT; #2; check(16'h0000, 0, 10); control_plane = 6'b0; #2;
        control_plane = R2_OUT; #2; check(16'h0000, 0, 10); control_plane = 6'b0; #2;
        control_plane = R3_OUT; #2; check(16'h0000, 0, 10); control_plane = 6'b0;

        // --------------------------------------------------
        // Test 11: Register independence
        // --------------------------------------------------
        $display("--- Test 11: Register independence ---");
        immediate = 16'hAABB; control_plane = R1_LOAD; tick; control_plane = 6'b0; #2;
        immediate = 16'hCCDD; control_plane = R2_LOAD; tick; control_plane = 6'b0; #2;
        immediate = 16'hEEFF; control_plane = R3_LOAD; tick; control_plane = 6'b0; #2;
        control_plane = R1_OUT; #2; check(16'hAABB, 0, 11); control_plane = 6'b0; #2;
        control_plane = R2_OUT; #2; check(16'hCCDD, 0, 11); control_plane = 6'b0; #2;
        control_plane = R3_OUT; #2; check(16'hEEFF, 0, 11); control_plane = 6'b0;

        // --------------------------------------------------
        // Test 12: Bus contention — two registers output simultaneously
        // --------------------------------------------------
        $display("--- Test 12: Bus contention (R1 + R2 tri simultaneously) ---");
        control_plane = R1_OUT | R2_OUT;
        #2;
        $display("INFO [Test 12] Contention result (expect X): %0h", shared_bus);
        control_plane = 6'b000000;

        #20;
        $display("Integration testbench complete.");
        $finish;
    end

    initial begin
        $dumpfile("tb_integration.vcd");
        $dumpvars(0, tb_integration);
    end

endmodule

tb_integration.vcd
$date
	Wed May 13 13:43:32 2026
$end
$version
	Icarus Verilog
$end
$timescale
	1ps
$end
$scope module tb_integration $end
$var wire 16 ! shared_bus [15:0] $end
$var wire 1 " bus_en $end
$var parameter 6 # R1_LOAD $end
$var parameter 6 $ R1_OUT $end
$var parameter 6 % R2_LOAD $end
$var parameter 6 & R2_OUT $end
$var parameter 6 ' R3_LOAD $end
$var parameter 6 ( R3_OUT $end
$var reg 1 ) clk $end
$var reg 6 * control_plane [5:0] $end
$var reg 16 + immediate [15:0] $end
$var reg 1 , rst $end
$scope module mux $end
$var wire 16 - immediate [15:0] $end
$var wire 1 " bus_en $end
$var reg 16 . bus_out [15:0] $end
$upscope $end
$scope module rf $end
$var wire 1 " bus_en $end
$var wire 1 ) clk $end
$var wire 6 / control_plane [5:0] $end
$var wire 16 0 input_bus [15:0] $end
$var wire 16 1 output_bus [15:0] $end
$var wire 1 , rst $end
$var wire 1 2 R3_tri $end
$var wire 1 3 R3_en $end
$var wire 1 4 R2_tri $end
$var wire 1 5 R2_en $end
$var wire 1 6 R1_tri $end
$var wire 1 7 R1_en $end
$scope module R1 $end
$var wire 1 ) clk $end
$var wire 16 8 d [15:0] $end
$var wire 1 7 load $end
$var wire 16 9 o [15:0] $end
$var wire 1 6 o_en $end
$var wire 1 , rst $end
$var reg 16 : data_wire [15:0] $end
$upscope $end
$scope module R2 $end
$var wire 1 ) clk $end
$var wire 16 ; d [15:0] $end
$var wire 1 5 load $end
$var wire 16 < o [15:0] $end
$var wire 1 4 o_en $end
$var wire 1 , rst $end
$var reg 16 = data_wire [15:0] $end
$upscope $end
$scope module R3 $end
$var wire 1 ) clk $end
$var wire 16 > d [15:0] $end
$var wire 1 3 load $end
$var wire 16 ? o [15:0] $end
$var wire 1 2 o_en $end
$var wire 1 , rst $end
$var reg 16 @ data_wire [15:0] $end
$upscope $end
$upscope $end
$scope task check $end
$var reg 1 A expect_hiz $end
$var reg 16 B expected [15:0] $end
$var reg 64 C test_num [63:0] $end
$upscope $end
$scope task tick $end
$upscope $end
$upscope $end
$enddefinitions $end
$comment Show the parameter values. $end
$dumpall
b1 (
b10 '
b100 &
b1000 %
b10000 $
b100000 #
$end
#0
$dumpvars
bx C
bx B
xA
b0 @
b0 ?
b0 >
b0 =
b0 <
b0 ;
b0 :
b0 9
b0 8
07
06
05
04
03
02
b0 1
b0 0
b0 /
b0 .
b0 -
1,
b0 +
b0 *
0)
0"
b0 !
$end
#5000
1)
#10000
0)
#15000
1)
#16000
bz .
1"
16
b10000 *
b10000 /
0,
#18000
b0 .
0"
b0 !
b0 0
b0 1
b0 8
b0 9
b0 ;
b0 <
b0 >
b0 ?
06
b0 *
b0 /
b1 C
0A
b0 B
#20000
bz .
1"
14
b100 *
b100 /
0)
#22000
b0 .
0"
b0 !
b0 0
b0 1
b0 8
b0 9
b0 ;
b0 <
b0 >
b0 ?
04
b0 *
b0 /
#24000
bz .
1"
12
b1 *
b1 /
#25000
1)
#26000
b0 .
b0 !
b0 0
b0 1
b0 8
b0 9
b0 ;
b0 <
b0 >
b0 ?
0"
02
b0 *
b0 /
#28000
17
b1010101010101010 !
b1010101010101010 0
b1010101010101010 1
b1010101010101010 8
b1010101010101010 9
b1010101010101010 ;
b1010101010101010 <
b1010101010101010 >
b1010101010101010 ?
b1010101010101010 .
b100000 *
b100000 /
b1010101010101010 +
b1010101010101010 -
#30000
0)
#35000
b1010101010101010 :
1)
#36000
bz .
1"
16
07
b10000 *
b10000 /
#38000
b1001000110100 .
0"
b1001000110100 !
b1001000110100 0
b1001000110100 1
b1001000110100 8
b1001000110100 9
b1001000110100 ;
b1001000110100 <
b1001000110100 >
b1001000110100 ?
15
06
b1001000110100 +
b1001000110100 -
b1000 *
b1000 /
b11 C
b1010101010101010 B
#40000
0)
#45000
b1001000110100 =
1)
#46000
bz .
1"
14
05
b100 *
b100 /
#48000
b101011001111000 .
0"
b101011001111000 !
b101011001111000 0
b101011001111000 1
b101011001111000 8
b101011001111000 9
b101011001111000 ;
b101011001111000 <
b101011001111000 >
b101011001111000 ?
13
04
b101011001111000 +
b101011001111000 -
b10 *
b10 /
b101 C
b1001000110100 B
#50000
0)
#55000
b101011001111000 @
1)
#56000
bz .
1"
12
03
b1 *
b1 /
#58000
b1010101010101010 .
b1010101010101010 !
b1010101010101010 0
b1010101010101010 1
b1010101010101010 8
b1010101010101010 9
b1010101010101010 ;
b1010101010101010 <
b1010101010101010 >
b1010101010101010 ?
0"
17
02
b1010101010101010 +
b1010101010101010 -
b100000 *
b100000 /
b111 C
b101011001111000 B
#60000
0)
#65000
1)
#66000
07
b0 *
b0 /
#68000
bz .
1"
16
15
b11000 *
b11000 /
#70000
0)
#75000
b1010101010101010 =
1)
#76000
b1010101010101010 .
0"
b1010101010101010 !
b1010101010101010 0
b1010101010101010 1
b1010101010101010 8
b1010101010101010 9
b1010101010101010 ;
b1010101010101010 <
b1010101010101010 >
b1010101010101010 ?
06
05
b0 *
b0 /
#78000
bz .
1"
14
b100 *
b100 /
#80000
b1010101010101010 .
0"
b1010101010101010 !
b1010101010101010 0
b1010101010101010 1
b1010101010101010 8
b1010101010101010 9
b1010101010101010 ;
b1010101010101010 <
b1010101010101010 >
b1010101010101010 ?
04
b0 *
b0 /
b1000 C
b1010101010101010 B
0)
#82000
bz .
1"
16
b10000 *
b10000 /
#84000
b1011111011101111 .
0"
b1011111011101111 !
b1011111011101111 0
b1011111011101111 1
b1011111011101111 8
b1011111011101111 9
b1011111011101111 ;
b1011111011101111 <
b1011111011101111 >
b1011111011101111 ?
17
15
13
06
b1011111011101111 +
b1011111011101111 -
b101010 *
b101010 /
#85000
b1011111011101111 @
b1011111011101111 =
b1011111011101111 :
1)
#86000
07
05
03
b0 *
b0 /
#88000
bz .
1"
16
b10000 *
b10000 /
#90000
b1011111011101111 .
0"
b1011111011101111 !
b1011111011101111 0
b1011111011101111 1
b1011111011101111 8
b1011111011101111 9
b1011111011101111 ;
b1011111011101111 <
b1011111011101111 >
b1011111011101111 ?
06
b0 *
b0 /
b1001 C
b1011111011101111 B
0)
#92000
bz .
1"
14
b100 *
b100 /
#94000
b1011111011101111 .
0"
b1011111011101111 !
b1011111011101111 0
b1011111011101111 1
b1011111011101111 8
b1011111011101111 9
b1011111011101111 ;
b1011111011101111 <
b1011111011101111 >
b1011111011101111 ?
04
b0 *
b0 /
#95000
1)
#96000
bz .
1"
12
b1 *
b1 /
#98000
b1101111010101101 .
b1101111010101101 !
b1101111010101101 0
b1101111010101101 1
b1101111010101101 8
b1101111010101101 9
b1101111010101101 ;
b1101111010101101 <
b1101111010101101 >
b1101111010101101 ?
0"
17
15
02
b1101111010101101 +
b1101111010101101 -
b101000 *
b101000 /
#100000
0)
#105000
b1101111010101101 =
b1101111010101101 :
1)
#106000
b0 :
b0 =
b0 @
07
05
1,
b0 *
b0 /
#110000
0)
#115000
1)
#116000
bz .
1"
b0 !
b0 0
b0 1
b0 8
b0 9
b0 ;
b0 <
b0 >
b0 ?
16
b10000 *
b10000 /
0,
#118000
b1101111010101101 .
0"
b1101111010101101 !
b1101111010101101 0
b1101111010101101 1
b1101111010101101 8
b1101111010101101 9
b1101111010101101 ;
b1101111010101101 <
b1101111010101101 >
b1101111010101101 ?
06
b0 *
b0 /
b1010 C
b0 B
#120000
bz .
1"
b0 !
b0 0
b0 1
b0 8
b0 9
b0 ;
b0 <
b0 >
b0 ?
14
b100 *
b100 /
0)
#122000
b1101111010101101 .
0"
b1101111010101101 !
b1101111010101101 0
b1101111010101101 1
b1101111010101101 8
b1101111010101101 9
b1101111010101101 ;
b1101111010101101 <
b1101111010101101 >
b1101111010101101 ?
04
b0 *
b0 /
#124000
bz .
b0 !
b0 0
b0 1
b0 8
b0 9
b0 ;
b0 <
b0 >
b0 ?
1"
12
b1 *
b1 /
#125000
1)
#126000
b1010101010111011 .
b1010101010111011 !
b1010101010111011 0
b1010101010111011 1
b1010101010111011 8
b1010101010111011 9
b1010101010111011 ;
b1010101010111011 <
b1010101010111011 >
b1010101010111011 ?
0"
17
02
b1010101010111011 +
b1010101010111011 -
b100000 *
b100000 /
#130000
0)
#135000
b1010101010111011 :
1)
#136000
07
b0 *
b0 /
#138000
15
b1100110011011101 !
b1100110011011101 0
b1100110011011101 1
b1100110011011101 8
b1100110011011101 9
b1100110011011101 ;
b1100110011011101 <
b1100110011011101 >
b1100110011011101 ?
b1100110011011101 .
b1000 *
b1000 /
b1100110011011101 +
b1100110011011101 -
#140000
0)
#145000
b1100110011011101 =
1)
#146000
05
b0 *
b0 /
#148000
13
b1110111011111111 !
b1110111011111111 0
b1110111011111111 1
b1110111011111111 8
b1110111011111111 9
b1110111011111111 ;
b1110111011111111 <
b1110111011111111 >
b1110111011111111 ?
b1110111011111111 .
b10 *
b10 /
b1110111011111111 +
b1110111011111111 -
#150000
0)
#155000
b1110111011111111 @
1)
#156000
03
b0 *
b0 /
#158000
bz .
1"
b1010101010111011 !
b1010101010111011 0
b1010101010111011 1
b1010101010111011 8
b1010101010111011 9
b1010101010111011 ;
b1010101010111011 <
b1010101010111011 >
b1010101010111011 ?
16
b10000 *
b10000 /
#160000
b1110111011111111 .
0"
b1110111011111111 !
b1110111011111111 0
b1110111011111111 1
b1110111011111111 8
b1110111011111111 9
b1110111011111111 ;
b1110111011111111 <
b1110111011111111 >
b1110111011111111 ?
06
b0 *
b0 /
b1011 C
b1010101010111011 B
0)
#162000
bz .
1"
b1100110011011101 !
b1100110011011101 0
b1100110011011101 1
b1100110011011101 8
b1100110011011101 9
b1100110011011101 ;
b1100110011011101 <
b1100110011011101 >
b1100110011011101 ?
14
b100 *
b100 /
#164000
b1110111011111111 .
0"
b1110111011111111 !
b1110111011111111 0
b1110111011111111 1
b1110111011111111 8
b1110111011111111 9
b1110111011111111 ;
b1110111011111111 <
b1110111011111111 >
b1110111011111111 ?
04
b0 *
b0 /
b1100110011011101 B
#165000
1)
#166000
bz .
1"
12
b1 *
b1 /
#168000
bz .
b1xx01xx01xx11xx1 !
b1xx01xx01xx11xx1 0
b1xx01xx01xx11xx1 1
b1xx01xx01xx11xx1 8
b1xx01xx01xx11xx1 9
b1xx01xx01xx11xx1 ;
b1xx01xx01xx11xx1 <
b1xx01xx01xx11xx1 >
b1xx01xx01xx11xx1 ?
1"
16
14
02
b10100 *
b10100 /
b1110111011111111 B
#170000
b1110111011111111 .
0"
b1110111011111111 !
b1110111011111111 0
b1110111011111111 1
b1110111011111111 8
b1110111011111111 9
b1110111011111111 ;
b1110111011111111 <
b1110111011111111 >
b1110111011111111 ?
06
04
b0 *
b0 /
0)
