hardware/tri_state_buffer.v
module tri_state_buffer(
    input enable,
    input [15:0] data,
    output [15:0] out
);
    // if not enabled disconnect the connection of the output
    // represents high impedance of the wire.
    assign out = enable ? data : 16'bz;
endmodule

tests/tsb_tb.v
module tri_state_buffer_tb();
    reg enable;
    reg clk;
    reg [4:0] counter;
    reg [15:0] bus;
    wire [15:0] o;

    tri_state_buffer buff(.enable(enable), .data(bus), .out(o));
    
    initial begin
        $dumpfile("tsb.vcd");
        $dumpvars(0, tri_state_buffer_tb);

        // Initialise them all to zero
        clk = 1'b0;
        enable = 1'b0;
        bus = 16'bx;
        counter = 5'd0;
        #20000;
        $finish;
    end

    always #5 clk = ~clk;

    always @(posedge clk) begin 
        counter <= counter + 1;
    end

    always @(counter) begin
        if (counter[0] == 1'b1) begin // Store data
            bus <= counter;
            enable <= 1'b1;
        end else if (counter[2] == 1'b1) begin // Adding Junk Data
            bus <= $random;
            enable <= 1'b0;
        end else begin // Adding other invalid data
            bus <= 16'bx;
            enable <= 1'b0;
        end 
    end
endmodule

tsb.vcd
$date
	Wed May  6 00:35:39 2026
$end
$version
	Icarus Verilog
$end
$timescale
	1s
$end
$scope module tri_state_buffer_tb $end
$var wire 16 ! o [15:0] $end
$var reg 16 " bus [15:0] $end
$var reg 1 # clk $end
$var reg 5 $ counter [4:0] $end
$var reg 1 % enable $end
$scope module buff $end
$var wire 16 & data [15:0] $end
$var wire 1 % enable $end
$var wire 16 ' out [15:0] $end
$upscope $end
$upscope $end
$enddefinitions $end
$comment Show the parameter values. $end
$dumpall
$end
#0
$dumpvars
bz '
bx &
0%
b0 $
0#
bx "
bz !
$end
#5
b1 !
b1 '
1%
b1 "
b1 &
b1 $
1#
#10
0#
#15
bz !
bz '
0%
bx "
bx &
b10 $
1#
#20
0#
#25
b11 !
b11 '
1%
b11 "
b11 &
b11 $
1#
#30
0#
#35
bz !
bz '
0%
b11010100100100 "
b11010100100100 &
b100 $
1#
#40
0#
#45
b101 !
b101 '
1%
b101 "
b101 &
b101 $
1#
#50
0#
#55
bz !
bz '
0%
b101111010000001 "
b101111010000001 &
b110 $
1#
#60
0#
#65
b111 !
b111 '
1%
b111 "
b111 &
b111 $
1#
#70
0#
#75
bz !
bz '
0%
bx "
bx &
b1000 $
1#
#80
0#
#85
b1001 !
b1001 '
1%
b1001 "
b1001 &
b1001 $
1#
#90
0#
#95
bz !
bz '
0%
bx "
bx &
b1010 $
1#
#100
0#
#105
b1011 !
b1011 '
1%
b1011 "
b1011 &
b1011 $
1#
#110
0#
#115
bz !
bz '
0%
b1101011000001001 "
b1101011000001001 &
b1100 $
1#
#120
0#
#125
b1101 !
b1101 '
1%
b1101 "
b1101 &
b1101 $
1#
#130
0#
#135
bz !
bz '
0%
b101011001100011 "
b101011001100011 &
b1110 $
1#
#140
0#
#145
b1111 !
b1111 '
1%
b1111 "
b1111 &
b1111 $
1#
#150
0#
#155
bz !
bz '
0%
bx "
bx &
b10000 $
1#
#160
0#
#165
b10001 !
b10001 '
1%
b10001 "
b10001 &
b10001 $
1#
#170
0#
#175
bz !
bz '
0%
bx "
bx &
b10010 $
1#
#180
0#
#185
b10011 !
b10011 '
1%
b10011 "
b10011 &
b10011 $
1#
#190
0#
#195
bz !
bz '
0%
b111101100001101 "
b111101100001101 &
b10100 $
1#
#200
0#
#205
b10101 !
b10101 '
1%
b10101 "
b10101 &
b10101 $
1#
#210
0#
#215
bz !
bz '
0%
b1001100110001101 "
b1001100110001101 &
b10110 $
1#
#220
0#
#225
b10111 !
b10111 '
1%
b10111 "
b10111 &
b10111 $
1#
#230
0#
#235
bz !
bz '
0%
bx "
bx &
b11000 $
1#
#240
0#
#245
b11001 !
b11001 '
1%
b11001 "
b11001 &
b11001 $
1#
#250
0#
#255
bz !
bz '
0%
bx "
bx &
b11010 $
1#
#260
0#
#265
b11011 !
b11011 '
1%
b11011 "
b11011 &
b11011 $
1#
#270
0#
#275
bz !
bz '
0%
b1000010001100101 "
b1000010001100101 &
b11100 $
1#
#280
0#
#285
b11101 !
b11101 '
1%
b11101 "
b11101 &
b11101 $
1#
#290
0#
#295
bz !
bz '
0%
b101001000010010 "
b101001000010010 &
b11110 $
1#
#300
0#
#305
b11111 !
b11111 '
1%
b11111 "
b11111 &
b11111 $
1#
#310
0#
#315
bz !
bz '
0%
bx "
bx &
b0 $
1#
#320
0#
#325
b1 !
b1 '
1%
b1 "
b1 &
b1 $
1#
#330
0#
#335
bz !
bz '
0%
bx "
bx &
b10 $
1#
#340
0#
#345
b11 !
b11 '
1%
b11 "
b11 &
b11 $
1#
#350
0#
#355
bz !
bz '
0%
b1110001100000001 "
b1110001100000001 &
b100 $
1#
#360
0#
#365
b101 !
b101 '
1%
b101 "
b101 &
b101 $
1#
#370
0#
#375
bz !
bz '
0%
b1100110100001101 "
b1100110100001101 &
b110 $
1#
#380
0#
#385
b111 !
b111 '
1%
b111 "
b111 &
b111 $
1#
#390
0#
#395
bz !
bz '
0%
bx "
bx &
b1000 $
1#
#400
0#
#405
b1001 !
b1001 '
1%
b1001 "
b1001 &
b1001 $
1#
#410
0#
#415
bz !
bz '
0%
bx "
bx &
b1010 $
1#
#420
0#
#425
b1011 !
b1011 '
1%
b1011 "
b1011 &
b1011 $
1#
#430
0#
#435
bz !
bz '
0%
b1111000101110110 "
b1111000101110110 &
b1100 $
1#
#440
0#
#445
b1101 !
b1101 '
1%
b1101 "
b1101 &
b1101 $
1#
#450
0#
#455
bz !
bz '
0%
b1100110100111101 "
b1100110100111101 &
b1110 $
1#
#460
0#
#465
b1111 !
b1111 '
1%
b1111 "
b1111 &
b1111 $
1#
#470
0#
#475
bz !
bz '
0%
bx "
bx &
b10000 $
1#
#480
0#
#485
b10001 !
b10001 '
1%
b10001 "
b10001 &
b10001 $
1#
#490
0#
#495
bz !
bz '
0%
bx "
bx &
b10010 $
1#
#500
0#
#505
b10011 !
b10011 '
1%
b10011 "
b10011 &
b10011 $
1#
#510
0#
#515
bz !
bz '
0%
b101011111101101 "
b101011111101101 &
b10100 $
1#
#520
0#
#525
b10101 !
b10101 '
1%
b10101 "
b10101 &
b10101 $
1#
#530
0#
#535
bz !
bz '
0%
b1111011110001100 "
b1111011110001100 &
b10110 $
1#
#540
0#
#545
b10111 !
b10111 '
1%
b10111 "
b10111 &
b10111 $
1#
#550
0#
#555
bz !
bz '
0%
bx "
bx &
b11000 $
1#
#560
0#
#565
b11001 !
b11001 '
1%
b11001 "
b11001 &
b11001 $
1#
#570
0#
#575
bz !
bz '
0%
bx "
bx &
b11010 $
1#
#580
0#
#585
b11011 !
b11011 '
1%
b11011 "
b11011 &
b11011 $
1#
#590
0#
#595
bz !
bz '
0%
b1110100111111001 "
b1110100111111001 &
b11100 $
1#
#600
0#
#605
b11101 !
b11101 '
1%
b11101 "
b11101 &
b11101 $
1#
#610
0#
#615
bz !
bz '
0%
b10010011000110 "
b10010011000110 &
b11110 $
1#
#620
0#
#625
b11111 !
b11111 '
1%
b11111 "
b11111 &
b11111 $
1#
#630
0#
#635
bz !
bz '
0%
bx "
bx &
b0 $
1#
#640
0#
#645
b1 !
b1 '
1%
b1 "
b1 &
b1 $
1#
#650
0#
#655
bz !
bz '
0%
bx "
bx &
b10 $
1#
#660
0#
#665
b11 !
b11 '
1%
b11 "
b11 &
b11 $
1#
#670
0#
#675
bz !
bz '
0%
b1000010011000101 "
b1000010011000101 &
b100 $
1#
#680
0#
#685
b101 !
b101 '
1%
b101 "
b101 &
b101 $
1#
#690
0#
#695
bz !
bz '
0%
b1101001010101010 "
b1101001010101010 &
b110 $
1#
#700
0#
#705
b111 !
b111 '
1%
b111 "
b111 &
b111 $
1#
#710
0#
#715
bz !
bz '
0%
bx "
bx &
b1000 $
1#
#720
0#
#725
b1001 !
b1001 '
1%
b1001 "
b1001 &
b1001 $
1#
#730
0#
#735
bz !
bz '
0%
bx "
bx &
b1010 $
1#
#740
0#
#745
b1011 !
b1011 '
1%
b1011 "
b1011 &
b1011 $
1#
#750
0#
#755
bz !
bz '
0%
b1111011111100101 "
b1111011111100101 &
b1100 $
1#
#760
0#
#765
b1101 !
b1101 '
1%
b1101 "
b1101 &
b1101 $
1#
#770
0#
#775
bz !
bz '
0%
b111001001110111 "
b111001001110111 &
b1110 $
1#
#780
0#
#785
b1111 !
b1111 '
1%
b1111 "
b1111 &
b1111 $
1#
#790
0#
#795
bz !
bz '
0%
bx "
bx &
b10000 $
1#
#800
0#
#805
b10001 !
b10001 '
1%
b10001 "
b10001 &
b10001 $
1#
#810
0#
#815
bz !
bz '
0%
bx "
bx &
b10010 $
1#
#820
0#
#825
b10011 !
b10011 '
1%
b10011 "
b10011 &
b10011 $
1#
#830
0#
#835
bz !
bz '
0%
b1101011000010010 "
b1101011000010010 &
b10100 $
1#
#840
0#
#845
b10101 !
b10101 '
1%
b10101 "
b10101 &
b10101 $
1#
#850
0#
#855
bz !
bz '
0%
b1101101110001111 "
b1101101110001111 &
b10110 $
1#
#860
0#
#865
b10111 !
b10111 '
1%
b10111 "
b10111 &
b10111 $
1#
#870
0#
#875
bz !
bz '
0%
bx "
bx &
b11000 $
1#
#880
0#
#885
b11001 !
b11001 '
1%
b11001 "
b11001 &
b11001 $
1#
#890
0#
#895
bz !
bz '
0%
bx "
bx &
b11010 $
1#
#900
0#
#905
b11011 !
b11011 '
1%
b11011 "
b11011 &
b11011 $
1#
#910
0#
#915
bz !
bz '
0%
b110100111110010 "
b110100111110010 &
b11100 $
1#
#920
0#
#925
b11101 !
b11101 '
1%
b11101 "
b11101 &
b11101 $
1#
#930
0#
#935
bz !
bz '
0%
b1001011011001110 "
b1001011011001110 &
b11110 $
1#
#940
0#
#945
b11111 !
b11111 '
1%
b11111 "
b11111 &
b11111 $
1#
#950
0#
#955
bz !
bz '
0%
bx "
bx &
b0 $
1#
#960
0#
#965
b1 !
b1 '
1%
b1 "
b1 &
b1 $
1#
#970
0#
#975
bz !
bz '
0%
bx "
bx &
b10 $
1#
#980
0#
#985
b11 !
b11 '
1%
b11 "
b11 &
b11 $
1#
#990
0#
#995
bz !
bz '
0%
b111101011101000 "
b111101011101000 &
b100 $
1#
#1000
0#
#1005
b101 !
b101 '
1%
b101 "
b101 &
b101 $
1#
#1010
0#
#1015
bz !
bz '
0%
b100111011000101 "
b100111011000101 &
b110 $
1#
#1020
0#
#1025
b111 !
b111 '
1%
b111 "
b111 &
b111 $
1#
#1030
0#
#1035
bz !
bz '
0%
bx "
bx &
b1000 $
1#
#1040
0#
#1045
b1001 !
b1001 '
1%
b1001 "
b1001 &
b1001 $
1#
#1050
0#
#1055
bz !
bz '
0%
bx "
bx &
b1010 $
1#
#1060
0#
#1065
b1011 !
b1011 '
1%
b1011 "
b1011 &
b1011 $
1#
#1070
0#
#1075
bz !
bz '
0%
b100100101011100 "
b100100101011100 &
b1100 $
1#
#1080
0#
#1085
b1101 !
b1101 '
1%
b1101 "
b1101 &
b1101 $
1#
#1090
0#
#1095
bz !
bz '
0%
b10100010111101 "
b10100010111101 &
b1110 $
1#
#1100
0#
#1105
b1111 !
b1111 '
1%
b1111 "
b1111 &
b1111 $
1#
#1110
0#
#1115
bz !
bz '
0%
bx "
bx &
b10000 $
1#
#1120
0#
#1125
b10001 !
b10001 '
1%
b10001 "
b10001 &
b10001 $
1#
#1130
0#
#1135
bz !
bz '
0%
bx "
bx &
b10010 $
1#
#1140
0#
#1145
b10011 !
b10011 '
1%
b10011 "
b10011 &
b10011 $
1#
#1150
0#
#1155
bz !
bz '
0%
b101100000101101 "
b101100000101101 &
b10100 $
1#
#1160
0#
#1165
b10101 !
b10101 '
1%
b10101 "
b10101 &
b10101 $
1#
#1170
0#
#1175
bz !
bz '
0%
b10011001100101 "
b10011001100101 &
b10110 $
1#
#1180
0#
#1185
b10111 !
b10111 '
1%
b10111 "
b10111 &
b10111 $
1#
#1190
0#
#1195
bz !
bz '
0%
bx "
bx &
b11000 $
1#
#1200
0#
#1205
b11001 !
b11001 '
1%
b11001 "
b11001 &
b11001 $
1#
#1210
0#
#1215
bz !
bz '
0%
bx "
bx &
b11010 $
1#
#1220
0#
#1225
b11011 !
b11011 '
1%
b11011 "
b11011 &
b11011 $
1#
#1230
0#
#1235
bz !
bz '
0%
b110001001100011 "
b110001001100011 &
b11100 $
1#
#1240
0#
#1245
b11101 !
b11101 '
1%
b11101 "
b11101 &
b11101 $
1#
#1250
0#
#1255
bz !
bz '
0%
b1000011100001010 "
b1000011100001010 &
b11110 $
1#
#1260
0#
#1265
b11111 !
b11111 '
1%
b11111 "
b11111 &
b11111 $
1#
#1270
0#
#1275
bz !
bz '
0%
bx "
bx &
b0 $
1#
#1280
0#
#1285
b1 !
b1 '
1%
b1 "
b1 &
b1 $
1#
#1290
0#
#1295
bz !
bz '
0%
bx "
bx &
b10 $
1#
#1300
0#
#1305
b11 !
b11 '
1%
b11 "
b11 &
b11 $
1#
#1310
0#
#1315
bz !
bz '
0%
b10001010000000 "
b10001010000000 &
b100 $
1#
#1320
0#
#1325
b101 !
b101 '
1%
b101 "
b101 &
b101 $
1#
#1330
0#
#1335
bz !
bz '
0%
b10000100100000 "
b10000100100000 &
b110 $
1#
#1340
0#
#1345
b111 !
b111 '
1%
b111 "
b111 &
b111 $
1#
#1350
0#
#1355
bz !
bz '
0%
bx "
bx &
b1000 $
1#
#1360
0#
#1365
b1001 !
b1001 '
1%
b1001 "
b1001 &
b1001 $
1#
#1370
0#
#1375
bz !
bz '
0%
bx "
bx &
b1010 $
1#
#1380
0#
#1385
b1011 !
b1011 '
1%
b1011 "
b1011 &
b1011 $
1#
#1390
0#
#1395
bz !
bz '
0%
b100010110101010 "
b100010110101010 &
b1100 $
1#
#1400
0#
#1405
b1101 !
b1101 '
1%
b1101 "
b1101 &
b1101 $
1#
#1410
0#
#1415
bz !
bz '
0%
b1100110010011101 "
b1100110010011101 &
b1110 $
1#
#1420
0#
#1425
b1111 !
b1111 '
1%
b1111 "
b1111 &
b1111 $
1#
#1430
0#
#1435
bz !
bz '
0%
bx "
bx &
b10000 $
1#
#1440
0#
#1445
b10001 !
b10001 '
1%
b10001 "
b10001 &
b10001 $
1#
#1450
0#
#1455
bz !
bz '
0%
bx "
bx &
b10010 $
1#
#1460
0#
#1465
b10011 !
b10011 '
1%
b10011 "
b10011 &
b10011 $
1#
#1470
0#
#1475
bz !
bz '
0%
b11111010010110 "
b11111010010110 &
b10100 $
1#
#1480
0#
#1485
b10101 !
b10101 '
1%
b10101 "
b10101 &
b10101 $
1#
#1490
0#
#1495
bz !
bz '
0%
b1011100000010011 "
b1011100000010011 &
b10110 $
1#
#1500
0#
#1505
b10111 !
b10111 '
1%
b10111 "
b10111 &
b10111 $
1#
#1510
0#
#1515
bz !
bz '
0%
bx "
bx &
b11000 $
1#
#1520
0#
#1525
b11001 !
b11001 '
1%
b11001 "
b11001 &
b11001 $
1#
#1530
0#
#1535
bz !
bz '
0%
bx "
bx &
b11010 $
1#
#1540
0#
#1545
b11011 !
b11011 '
1%
b11011 "
b11011 &
b11011 $
1#
#1550
0#
#1555
bz !
bz '
0%
b11100000001101 "
b11100000001101 &
b11100 $
1#
#1560
0#
#1565
b11101 !
b11101 '
1%
b11101 "
b11101 &
b11101 $
1#
#1570
0#
#1575
bz !
bz '
0%
b1101011001010011 "
b1101011001010011 &
b11110 $
1#
#1580
0#
#1585
b11111 !
b11111 '
1%
b11111 "
b11111 &
b11111 $
1#
#1590
0#
#1595
bz !
bz '
0%
bx "
bx &
b0 $
1#
#1600
0#
#1605
b1 !
b1 '
1%
b1 "
b1 &
b1 $
1#
#1610
0#
#1615
bz !
bz '
0%
bx "
bx &
b10 $
1#
#1620
0#
#1625
b11 !
b11 '
1%
b11 "
b11 &
b11 $
1#
#1630
0#
#1635
bz !
bz '
0%
b1101110101101011 "
b1101110101101011 &
b100 $
1#
#1640
0#
#1645
b101 !
b101 '
1%
b101 "
b101 &
b101 $
1#
#1650
0#
#1655
bz !
bz '
0%
b10101011010101 "
b10101011010101 &
b110 $
1#
#1660
0#
#1665
b111 !
b111 '
1%
b111 "
b111 &
b111 $
1#
#1670
0#
#1675
bz !
bz '
0%
bx "
bx &
b1000 $
1#
#1680
0#
#1685
b1001 !
b1001 '
1%
b1001 "
b1001 &
b1001 $
1#
#1690
0#
#1695
bz !
bz '
0%
bx "
bx &
b1010 $
1#
#1700
0#
#1705
b1011 !
b1011 '
1%
b1011 "
b1011 &
b1011 $
1#
#1710
0#
#1715
bz !
bz '
0%
b100101000000010 "
b100101000000010 &
b1100 $
1#
#1720
0#
#1725
b1101 !
b1101 '
1%
b1101 "
b1101 &
b1101 $
1#
#1730
0#
#1735
bz !
bz '
0%
b11111010101110 "
b11111010101110 &
b1110 $
1#
#1740
0#
#1745
b1111 !
b1111 '
1%
b1111 "
b1111 &
b1111 $
1#
#1750
0#
#1755
bz !
bz '
0%
bx "
bx &
b10000 $
1#
#1760
0#
#1765
b10001 !
b10001 '
1%
b10001 "
b10001 &
b10001 $
1#
#1770
0#
#1775
bz !
bz '
0%
bx "
bx &
b10010 $
1#
#1780
0#
#1785
b10011 !
b10011 '
1%
b10011 "
b10011 &
b10011 $
1#
#1790
0#
#1795
bz !
bz '
0%
b1110100100011101 "
b1110100100011101 &
b10100 $
1#
#1800
0#
#1805
b10101 !
b10101 '
1%
b10101 "
b10101 &
b10101 $
1#
#1810
0#
#1815
bz !
bz '
0%
b111001011001111 "
b111001011001111 &
b10110 $
1#
#1820
0#
#1825
b10111 !
b10111 '
1%
b10111 "
b10111 &
b10111 $
1#
#1830
0#
#1835
bz !
bz '
0%
bx "
bx &
b11000 $
1#
#1840
0#
#1845
b11001 !
b11001 '
1%
b11001 "
b11001 &
b11001 $
1#
#1850
0#
#1855
bz !
bz '
0%
bx "
bx &
b11010 $
1#
#1860
0#
#1865
b11011 !
b11011 '
1%
b11011 "
b11011 &
b11011 $
1#
#1870
0#
#1875
bz !
bz '
0%
b100100100100011 "
b100100100100011 &
b11100 $
1#
#1880
0#
#1885
b11101 !
b11101 '
1%
b11101 "
b11101 &
b11101 $
1#
#1890
0#
#1895
bz !
bz '
0%
b110010100001010 "
b110010100001010 &
b11110 $
1#
#1900
0#
#1905
b11111 !
b11111 '
1%
b11111 "
b11111 &
b11111 $
1#
#1910
0#
#1915
bz !
bz '
0%
bx "
bx &
b0 $
1#
#1920
0#
#1925
b1 !
b1 '
1%
b1 "
b1 &
b1 $
1#
#1930
0#
#1935
bz !
bz '
0%
bx "
bx &
b10 $
1#
#1940
0#
#1945
b11 !
b11 '
1%
b11 "
b11 &
b11 $
1#
#1950
0#
#1955
bz !
bz '
0%
b101011001010 "
b101011001010 &
b100 $
1#
#1960
0#
#1965
b101 !
b101 '
1%
b101 "
b101 &
b101 $
1#
#1970
0#
#1975
bz !
bz '
0%
b100110000111100 "
b100110000111100 &
b110 $
1#
#1980
0#
#1985
b111 !
b111 '
1%
b111 "
b111 &
b111 $
1#
#1990
0#
#1995
bz !
bz '
0%
bx "
bx &
b1000 $
1#
#2000
0#
#2005
b1001 !
b1001 '
1%
b1001 "
b1001 &
b1001 $
1#
#2010
0#
#2015
bz !
bz '
0%
bx "
bx &
b1010 $
1#
#2020
0#
#2025
b1011 !
b1011 '
1%
b1011 "
b1011 &
b1011 $
1#
#2030
0#
#2035
bz !
bz '
0%
b1011110111110010 "
b1011110111110010 &
b1100 $
1#
#2040
0#
#2045
b1101 !
b1101 '
1%
b1101 "
b1101 &
b1101 $
1#
#2050
0#
#2055
bz !
bz '
0%
b110000110001010 "
b110000110001010 &
b1110 $
1#
#2060
0#
#2065
b1111 !
b1111 '
1%
b1111 "
b1111 &
b1111 $
1#
#2070
0#
#2075
bz !
bz '
0%
bx "
bx &
b10000 $
1#
#2080
0#
#2085
b10001 !
b10001 '
1%
b10001 "
b10001 &
b10001 $
1#
#2090
0#
#2095
bz !
bz '
0%
bx "
bx &
b10010 $
1#
#2100
0#
#2105
b10011 !
b10011 '
1%
b10011 "
b10011 &
b10011 $
1#
#2110
0#
#2115
bz !
bz '
0%
b1011001101000001 "
b1011001101000001 &
b10100 $
1#
#2120
0#
#2125
b10101 !
b10101 '
1%
b10101 "
b10101 &
b10101 $
1#
#2130
0#
#2135
bz !
bz '
0%
b11010011011000 "
b11010011011000 &
b10110 $
1#
#2140
0#
#2145
b10111 !
b10111 '
1%
b10111 "
b10111 &
b10111 $
1#
#2150
0#
#2155
bz !
bz '
0%
bx "
bx &
b11000 $
1#
#2160
0#
#2165
b11001 !
b11001 '
1%
b11001 "
b11001 &
b11001 $
1#
#2170
0#
#2175
bz !
bz '
0%
bx "
bx &
b11010 $
1#
#2180
0#
#2185
b11011 !
b11011 '
1%
b11011 "
b11011 &
b11011 $
1#
#2190
0#
#2195
bz !
bz '
0%
b1111001101111000 "
b1111001101111000 &
b11100 $
1#
#2200
0#
#2205
b11101 !
b11101 '
1%
b11101 "
b11101 &
b11101 $
1#
#2210
0#
#2215
bz !
bz '
0%
b1001010001001 "
b1001010001001 &
b11110 $
1#
#2220
0#
#2225
b11111 !
b11111 '
1%
b11111 "
b11111 &
b11111 $
1#
#2230
0#
#2235
bz !
bz '
0%
bx "
bx &
b0 $
1#
#2240
0#
#2245
b1 !
b1 '
1%
b1 "
b1 &
b1 $
1#
#2250
0#
#2255
bz !
bz '
0%
bx "
bx &
b10 $
1#
#2260
0#
#2265
b11 !
b11 '
1%
b11 "
b11 &
b11 $
1#
#2270
0#
#2275
bz !
bz '
0%
b110111101011 "
b110111101011 &
b100 $
1#
#2280
0#
#2285
b101 !
b101 '
1%
b101 "
b101 &
b101 $
1#
#2290
0#
#2295
bz !
bz '
0%
b110010110110110 "
b110010110110110 &
b110 $
1#
#2300
0#
#2305
b111 !
b111 '
1%
b111 "
b111 &
b111 $
1#
#2310
0#
#2315
bz !
bz '
0%
bx "
bx &
b1000 $
1#
#2320
0#
#2325
b1001 !
b1001 '
1%
b1001 "
b1001 &
b1001 $
1#
#2330
0#
#2335
bz !
bz '
0%
bx "
bx &
b1010 $
1#
#2340
0#
#2345
b1011 !
b1011 '
1%
b1011 "
b1011 &
b1011 $
1#
#2350
0#
#2355
bz !
bz '
0%
b1111100111000110 "
b1111100111000110 &
b1100 $
1#
#2360
0#
#2365
b1101 !
b1101 '
1%
b1101 "
b1101 &
b1101 $
1#
#2370
0#
#2375
bz !
bz '
0%
b1001110101110 "
b1001110101110 &
b1110 $
1#
#2380
0#
#2385
b1111 !
b1111 '
1%
b1111 "
b1111 &
b1111 $
1#
#2390
0#
#2395
bz !
bz '
0%
bx "
bx &
b10000 $
1#
#2400
0#
#2405
b10001 !
b10001 '
1%
b10001 "
b10001 &
b10001 $
1#
#2410
0#
#2415
bz !
bz '
0%
bx "
bx &
b10010 $
1#
#2420
0#
#2425
b10011 !
b10011 '
1%
b10011 "
b10011 &
b10011 $
1#
#2430
0#
#2435
bz !
bz '
0%
b1010111100 "
b1010111100 &
b10100 $
1#
#2440
0#
#2445
b10101 !
b10101 '
1%
b10101 "
b10101 &
b10101 $
1#
#2450
0#
#2455
bz !
bz '
0%
b1101110100101010 "
b1101110100101010 &
b10110 $
1#
#2460
0#
#2465
b10111 !
b10111 '
1%
b10111 "
b10111 &
b10111 $
1#
#2470
0#
#2475
bz !
bz '
0%
bx "
bx &
b11000 $
1#
#2480
0#
#2485
b11001 !
b11001 '
1%
b11001 "
b11001 &
b11001 $
1#
#2490
0#
#2495
bz !
bz '
0%
bx "
bx &
b11010 $
1#
#2500
0#
#2505
b11011 !
b11011 '
1%
b11011 "
b11011 &
b11011 $
1#
#2510
0#
#2515
bz !
bz '
0%
b1001101000001011 "
b1001101000001011 &
b11100 $
1#
#2520
0#
#2525
b11101 !
b11101 '
1%
b11101 "
b11101 &
b11101 $
1#
#2530
0#
#2535
bz !
bz '
0%
b1011111001110001 "
b1011111001110001 &
b11110 $
1#
#2540
0#
#2545
b11111 !
b11111 '
1%
b11111 "
b11111 &
b11111 $
1#
#2550
0#
#2555
bz !
bz '
0%
bx "
bx &
b0 $
1#
#2560
0#
#2565
b1 !
b1 '
1%
b1 "
b1 &
b1 $
1#
#2570
0#
#2575
bz !
bz '
0%
bx "
bx &
b10 $
1#
#2580
0#
#2585
b11 !
b11 '
1%
b11 "
b11 &
b11 $
1#
#2590
0#
#2595
bz !
bz '
0%
b100000110000101 "
b100000110000101 &
b100 $
1#
#2600
0#
#2605
b101 !
b101 '
1%
b101 "
b101 &
b101 $
1#
#2610
0#
#2615
bz !
bz '
0%
b101010101001111 "
b101010101001111 &
b110 $
1#
#2620
0#
#2625
b111 !
b111 '
1%
b111 "
b111 &
b111 $
1#
#2630
0#
#2635
bz !
bz '
0%
bx "
bx &
b1000 $
1#
#2640
0#
#2645
b1001 !
b1001 '
1%
b1001 "
b1001 &
b1001 $
1#
#2650
0#
#2655
bz !
bz '
0%
bx "
bx &
b1010 $
1#
#2660
0#
#2665
b1011 !
b1011 '
1%
b1011 "
b1011 &
b1011 $
1#
#2670
0#
#2675
bz !
bz '
0%
b110000000111011 "
b110000000111011 &
b1100 $
1#
#2680
0#
#2685
b1101 !
b1101 '
1%
b1101 "
b1101 &
b1101 $
1#
#2690
0#
#2695
bz !
bz '
0%
b11001100111010 "
b11001100111010 &
b1110 $
1#
#2700
0#
#2705
b1111 !
b1111 '
1%
b1111 "
b1111 &
b1111 $
1#
#2710
0#
#2715
bz !
bz '
0%
bx "
bx &
b10000 $
1#
#2720
0#
#2725
b10001 !
b10001 '
1%
b10001 "
b10001 &
b10001 $
1#
#2730
0#
#2735
bz !
bz '
0%
bx "
bx &
b10010 $
1#
#2740
0#
#2745
b10011 !
b10011 '
1%
b10011 "
b10011 &
b10011 $
1#
#2750
0#
#2755
bz !
bz '
0%
b11001001111110 "
b11001001111110 &
b10100 $
1#
#2760
0#
#2765
b10101 !
b10101 '
1%
b10101 "
b10101 &
b10101 $
1#
#2770
0#
#2775
bz !
bz '
0%
b100101100010101 "
b100101100010101 &
b10110 $
1#
#2780
0#
#2785
b10111 !
b10111 '
1%
b10111 "
b10111 &
b10111 $
1#
#2790
0#
#2795
bz !
bz '
0%
bx "
bx &
b11000 $
1#
#2800
0#
#2805
b11001 !
b11001 '
1%
b11001 "
b11001 &
b11001 $
1#
#2810
0#
#2815
bz !
bz '
0%
bx "
bx &
b11010 $
1#
#2820
0#
#2825
b11011 !
b11011 '
1%
b11011 "
b11011 &
b11011 $
1#
#2830
0#
#2835
bz !
bz '
0%
b1001101111110001 "
b1001101111110001 &
b11100 $
1#
#2840
0#
#2845
b11101 !
b11101 '
1%
b11101 "
b11101 &
b11101 $
1#
#2850
0#
#2855
bz !
bz '
0%
b100101111011001 "
b100101111011001 &
b11110 $
1#
#2860
0#
#2865
b11111 !
b11111 '
1%
b11111 "
b11111 &
b11111 $
1#
#2870
0#
#2875
bz !
bz '
0%
bx "
bx &
b0 $
1#
#2880
0#
#2885
b1 !
b1 '
1%
b1 "
b1 &
b1 $
1#
#2890
0#
#2895
bz !
bz '
0%
bx "
bx &
b10 $
1#
#2900
0#
#2905
b11 !
b11 '
1%
b11 "
b11 &
b11 $
1#
#2910
0#
#2915
bz !
bz '
0%
b11101100010 "
b11101100010 &
b100 $
1#
#2920
0#
#2925
b101 !
b101 '
1%
b101 "
b101 &
b101 $
1#
#2930
0#
#2935
bz !
bz '
0%
b1111101101001100 "
b1111101101001100 &
b110 $
1#
#2940
0#
#2945
b111 !
b111 '
1%
b111 "
b111 &
b111 $
1#
#2950
0#
#2955
bz !
bz '
0%
bx "
bx &
b1000 $
1#
#2960
0#
#2965
b1001 !
b1001 '
1%
b1001 "
b1001 &
b1001 $
1#
#2970
0#
#2975
bz !
bz '
0%
bx "
bx &
b1010 $
1#
#2980
0#
#2985
b1011 !
b1011 '
1%
b1011 "
b1011 &
b1011 $
1#
#2990
0#
#2995
bz !
bz '
0%
b101010110011111 "
b101010110011111 &
b1100 $
1#
#3000
0#
#3005
b1101 !
b1101 '
1%
b1101 "
b1101 &
b1101 $
1#
#3010
0#
#3015
bz !
bz '
0%
b1010000110001111 "
b1010000110001111 &
b1110 $
1#
#3020
0#
#3025
b1111 !
b1111 '
1%
b1111 "
b1111 &
b1111 $
1#
#3030
0#
#3035
bz !
bz '
0%
bx "
bx &
b10000 $
1#
#3040
0#
#3045
b10001 !
b10001 '
1%
b10001 "
b10001 &
b10001 $
1#
#3050
0#
#3055
bz !
bz '
0%
bx "
bx &
b10010 $
1#
#3060
0#
#3065
b10011 !
b10011 '
1%
b10011 "
b10011 &
b10011 $
1#
#3070
0#
#3075
bz !
bz '
0%
b1010100111111000 "
b1010100111111000 &
b10100 $
1#
#3080
0#
#3085
b10101 !
b10101 '
1%
b10101 "
b10101 &
b10101 $
1#
#3090
0#
#3095
bz !
bz '
0%
b110000010110111 "
b110000010110111 &
b10110 $
1#
#3100
0#
#3105
b10111 !
b10111 '
1%
b10111 "
b10111 &
b10111 $
1#
#3110
0#
#3115
bz !
bz '
0%
bx "
bx &
b11000 $
1#
#3120
0#
#3125
b11001 !
b11001 '
1%
b11001 "
b11001 &
b11001 $
1#
#3130
0#
#3135
bz !
bz '
0%
bx "
bx &
b11010 $
1#
#3140
0#
#3145
b11011 !
b11011 '
1%
b11011 "
b11011 &
b11011 $
1#
#3150
0#
#3155
bz !
bz '
0%
b101011010011111 "
b101011010011111 &
b11100 $
1#
#3160
0#
#3165
b11101 !
b11101 '
1%
b11101 "
b11101 &
b11101 $
1#
#3170
0#
#3175
bz !
bz '
0%
b1001010001011100 "
b1001010001011100 &
b11110 $
1#
#3180
0#
#3185
b11111 !
b11111 '
1%
b11111 "
b11111 &
b11111 $
1#
#3190
0#
