LUKE AND JASON/luke/hardware_chat/bus_mux.v
`timescale 1ns / 1ps

// Selects which value goes onto the processor bus
// bus_sel = 000 → bus = R0
// bus_sel = 001 → bus = R1
// bus_sel = 010 → bus = R2
// bus_sel = 011 → bus = G
// bus_sel = 100 → bus = immediate


module bus_mux(

    input [15:0] R0_data,
    input [15:0] R1_data,
    input [15:0] R2_data,
    input [15:0] G_data,
    input [15:0] immediate,
    input [2:0] bus_sel,
    output reg [15:0] bus_out

);

    // Bus select codes

    parameter BUS_R0  = 3'b000;
    parameter BUS_R1  = 3'b001;
    parameter BUS_R2  = 3'b010;
    parameter BUS_G   = 3'b011;
    parameter BUS_IMM = 3'b100;

    always @(*) begin

        case (bus_sel)
            BUS_R0: begin
                bus_out = R0_data;
            end
            BUS_R1: begin
                bus_out = R1_data;
            end
            BUS_R2: begin
                bus_out = R2_data;
            end
            BUS_G: begin
                bus_out = G_data;
            end
            BUS_IMM: begin
                bus_out = immediate;
            end
            default: begin
                bus_out = 16'd0;
            end
        endcase
    end

endmodule

LUKE AND JASON/luke/extension/register_16.v
`timescale 1ns / 1ps

// 16-bit register module
// Used for R0, R1, R2, A and G registers

module register_16(

    input clk,            // Clock signal
    input rst,            // Reset signal
    input en,             // Enable signal: allows register to store new data

    input [15:0] D,       // 16-bit input data

    output reg [15:0] Q   // 16-bit stored output value
);

// Register updates only on:
// 1. Rising clock edge
// 2. Rising reset edge

always @(posedge clk or posedge rst) begin
    // Reset register value back to 0
    if (rst) begin
        Q <= 16'd0;
    end
    // Store new value only if enable is ON
    else if (en) begin
        Q <= D;
    end
    // If enable = 0:
    // keep previous stored value automatically

end

endmodule

LUKE AND JASON/luke/hardware_chat/ALU.v
module ALU (
    input [15:0] A,
    input [15:0] B,
    input alu_ctl,
    output reg [15:0] Y
);

always @(*) begin
    case (alu_ctl)
        1'b0: Y = A + B;
        1'b1: Y = A - B;
    endcase
end

endmodule

LUKE AND JASON/luke/extension/register_file.v
`timescale 1ns / 1ps

// Register file module
// Contains general purpose registers:
// R0, R1 and R2

module register_file(

    input clk,                 // Clock signal
    input rst,                 // Reset signal

    input [15:0] bus_in,       // Data coming from the processor bus

    // Enable signals for each register
    // If enable = 1, register stores bus_in value
    input R0_en,
    input R1_en,
    input R2_en,

    // Current stored values of registers
    output [15:0] R0_out,
    output [15:0] R1_out,
    output [15:0] R2_out
);

    // Register R0
    register_16 R0_reg(

        .clk(clk),         // Shared processor clock
        .rst(rst),         // Reset R0 back to 0
        .en(R0_en),        // Store data only when enabled

        .D(bus_in),        // Data entering R0 from bus
        .Q(R0_out)         // Current stored value of R0
    );


    // Register R1
    register_16 R1_reg(

        .clk(clk),
        .rst(rst),
        .en(R1_en),

        .D(bus_in),
        .Q(R1_out)
    );

    // Register R2
    register_16 R2_reg(

        .clk(clk),
        .rst(rst),
        .en(R2_en),

        .D(bus_in),
        .Q(R2_out)
    );

endmodule

LUKE AND JASON/luke/hardware_chat/controller_fsm.v
`timescale 1ns / 1ps

// Controller FSM
// Controls execution of:
// LDI, MOV, ADD and SUB instructions

module controller_fsm(
    input clk,
    input rst,
    input run,
/*
clk moves the FSm from one state to the next 
rst send it back to IDLE 
run tell ths FSM to state executing an instruction 
*/

    // Instruction fields
    input [1:0] opcode,
    input [1:0] rx,
    input [1:0] ry,
/*
opcode tells the FSM which instructions: LDI, MOV, ADD or SUB  (e.g. ADD R0, R1)
rx is the destiantion register (e.g. rx = R0)
ry is the source register  (e.g. ry = R1)
*/
    // Control outputs
    output reg [2:0] bus_sel,
    output reg R0_en,
    output reg R1_en,
    output reg R2_en,
/*
27 choese which goes onto the bus (28,29,30)
*/

    output reg A_en,
    output reg G_en,
/*
A_en stores the first ALU input 
G_en stores the ALU input 
*/

    output reg alu_op,
    output reg done
/*
42 choses the ALU operation (0 = Add, 1 = Sub)
goes high whne the instructions has finished. 
*/
    
);

    // Instruction opcodes
    parameter LDI = 2'b00;
    parameter MOV = 2'b01;
    parameter ADD = 2'b10;
    parameter SUB = 2'b11;
/*
Opcodes, the labels for instruction type.
*/
    // Bus select values
    parameter BUS_R0  = 3'b000;
    parameter BUS_R1  = 3'b001;
    parameter BUS_R2  = 3'b010;
    parameter BUS_G   = 3'b011;
    parameter BUS_IMM = 3'b100;
/*
Bus select values - these are labels for what source goes onto the bus
*/
    // FSM states
    parameter IDLE  = 3'b000;
    parameter EXEC1 = 3'b001;
    parameter EXEC2 = 3'b010;
    parameter EXEC3 = 3'b011;
    parameter DONE  = 3'b100;
/*
The FSm moves through these states 
IDLE = waiting
EXEC1 = first execution step 
EXEC2 = seconds execution step 
EXEC3 = third execution step 
DONE = instruction finsihed. 
*/

    reg [2:0] state;
    reg [2:0] next_state;

    // State register
    always @(posedge clk or posedge rst) begin
        if (rst)
            state <= IDLE;
        else
            state <= next_state;
    end
/*
on reset go back to IDLE,
otherwise on each of the clock edge, move to the calulated next_State. 
*/

    // Next state logic
    always @(*) begin
        case (state)
            IDLE: begin
                if (run)
                    next_state = EXEC1;
                else
                    next_state = IDLE;
            end
/*
Wait until run  = 1
*/

            EXEC1: begin
                // ADD and SUB need multiple states
                if (opcode == ADD || opcode == SUB)
                    next_state = EXEC2;
                // LDI and MOV finish immediately
                else
                    next_state = DONE;
            end
/*
LDI and MOV in one step 
ADd and SUB need more steps. 
*/

            EXEC2: begin
                next_state = EXEC3;
            end
/*
after ALU caluclation move to write back 
*/

            EXEC3: begin
                next_state = DONE;
            end
/*
after writing result back, instruction is done. 
*/

            DONE: begin
                next_state = IDLE;
            end
/*
retuns to waiting state.
*/

            default: begin
                next_state = IDLE;
            end
        endcase
    end

    // Output control logic
    always @(*) begin

        // Default values
        bus_sel = 3'b000;

        R0_en = 0;
        R1_en = 0;
        R2_en = 0;
        A_en = 0;
        G_en = 0;
        alu_op = 0;
        done = 0;
/*
prevents the old signal from staying on accidentally. 
*/

        case (state)
            // EXEC1
            EXEC1: begin
                case (opcode)
                    // LDI

                    LDI: begin
                        bus_sel = BUS_IMM;
                        case (rx)
                            2'b00: R0_en = 1;
                            2'b01: R1_en = 1;
                            2'b10: R2_en = 1;
                        endcase
                    end
/*
175 put immediate value on the bus 
then rx decided which register enables  (e.g. LDI R0, 5, -> immediate goes on bus, R0_en =1 )
*/

                    // MOV
                    MOV: begin
                        case (ry)
                            2'b00: bus_sel = BUS_R0;
                            2'b01: bus_sel = BUS_R1;
                            2'b10: bus_sel = BUS_R2;
                        endcase

                        case (rx)
                            2'b00: R0_en = 1;
                            2'b01: R1_en = 1;
                            2'b10: R2_en = 1;
                        endcase
                    end
/*
ry decided bus_sel 
rx decided register nable 
so then MOV R0, R1 -> R1 goes onthe bus, R0_en = 1
*/
                    // ADD / SUB
                    // Move Rx into A register
                    ADD,
                    SUB: begin
                        case (rx)
                            2'b00: bus_sel = BUS_R0;
                            2'b01: bus_sel = BUS_R1;
                            2'b10: bus_sel = BUS_R2;
                        endcase
                        A_en = 1;
                    end
                endcase
            end
/*
rx goes onto the bus A_en = 1 
ADD R0, R1 step 1: 
R0 -> bus -> A
*/
            // EXEC2
            // ALU operation
            EXEC2: begin
                case (ry)
                    2'b00: bus_sel = BUS_R0;
                    2'b01: bus_sel = BUS_R1;
                    2'b10: bus_sel = BUS_R2;
                endcase

                // SUB uses alu_op = 1
                if (opcode == SUB)
                    alu_op = 1'b1;
                G_en = 1;

            end

            // EXEC3
            // Write G back into Rx

            EXEC3: begin
                bus_sel = BUS_G;
                case (rx)
                    2'b00: R0_en = 1;
                    2'b01: R1_en = 1;
                    2'b10: R2_en = 1;
                endcase
            end
            // DONE

            DONE: begin
                done = 1;
            end

        endcase

    end

endmodule

LUKE AND JASON/luke/hardware_chat/processor_top.v
`timescale 1ns / 1ps

/*
// Top-level processor module
// Connects together:
// - Register file
// - A register
// - G register
// - ALU
// - Bus multiplexer
// - Controller FSM
*/

module processor_top(

    input clk,
    input rst,
    input run,
/*
clk - cotnrols the timing of the processor, registers and fsm update on clock edges 
rst - resets
run - starts the thing 
*/
    // Instruction inputs
    input [1:0] opcode,
    input [1:0] rx,
    input [1:0] ry,
/*
opcode instructions are (00, LDI) (01, MOV), (10, ADD), (11, SUB)
rx is the destination register
ry is the source register
*/
    // Immediate value for LDI
    input [15:0] immediate,
/*
used for LDI, such that LDI R0, 5 then immediate is 5
*/
    // Instruction finished signal
    output done
);

    // Internal BUS wire
    wire [15:0] bus;

    // Register outputs
    wire [15:0] R0_data;
    wire [15:0] R1_data;
    wire [15:0] R2_data;
/*
these hold the current valus of R0 R1 adn R2
*/

    // A register and G register outputs
    wire [15:0] A_data;
    wire [15:0] G_data;
/*
A_data stoes the first ALU operand
G-data states the ALU results
*/

    // ALU result
     wire [15:0] alu_result;
/*
temp wire that holds the ALU output
*/

    // FSM control signals
    wire [2:0] bus_sel;
    wire R0_en;
    wire R1_en;
    wire R2_en;
    wire A_en;
    wire G_en;
    wire alu_op;
/*
bus_sel - controls what goes on the bus
the R0-en stuff controls which register stores the BUS value. 
A_en and G_en, controls storing into A and G 
alu_op controls the add and the sub
*/

    // Controller FSM
    controller_fsm controller(

        .clk(clk),
        .rst(rst),
        .run(run),

        .opcode(opcode),
        .rx(rx),
        .ry(ry),

        .bus_sel(bus_sel),

        .R0_en(R0_en),
        .R1_en(R1_en),
        .R2_en(R2_en),

        .A_en(A_en),
        .G_en(G_en),

        .alu_op(alu_op),

        .done(done)
    );

    // Register file
    // Contains R0, R1 and R2
    /*
    creates R0 and R1 and R2
    */

    register_file reg_file(

        .clk(clk),
        .rst(rst),

        .bus_in(bus), // means whatever is on bus can enter registers

        .R0_en(R0_en),
        .R1_en(R1_en),
        .R2_en(R2_en),

        .R0_out(R0_data),
        .R1_out(R1_data),
        .R2_out(R2_data)
    );

    // A register
    // Stores first ALU operand

    register_16 A_reg(

        .clk(clk),
        .rst(rst),
        .en(A_en),

        .D(bus), // A register stores bus value
        .Q(A_data)
    );


    // ALU
    // Performs ADD and SUB
    ALU alu(

        .A(A_data),
        .B(bus),

        .alu_ctl(alu_op),

        .Y(alu_result)
    );

    // G register
    // Stores ALU result
    register_16 G_reg(

        .clk(clk),
        .rst(rst),
        .en(G_en),

        .D(alu_result), // stoes ALU result into G
        .Q(G_data)
    );

    // Bus multiplexer
    // Chooses what value goes onto BUS
    bus_mux mux(

        .R0_data(R0_data),
        .R1_data(R1_data),
        .R2_data(R2_data),

        .G_data(G_data),

        .immediate(immediate),

        .bus_sel(bus_sel),

        .bus_out(bus)
    );

endmodule

LUKE AND JASON/luke/hardware_chat/processor_TB.v
/*
LDI R0, 5
LDI R1, 3
ADD R0, R1     // R0 should become 8
SUB R0, R1     // R0 should become 5
MOV R2, R0     // R2 should become 5
were going to test these 5 things
*/

`timescale 1ns / 1ps

module processor_TB;

    reg clk;
    reg rst;
    reg run;

    reg [1:0] opcode;
    reg [1:0] rx;
    reg [1:0] ry;
    reg [15:0] immediate;

    wire done;

    // Opcodes
    parameter LDI = 2'b00; 
    parameter MOV = 2'b01;
    parameter ADD = 2'b10;
    parameter SUB = 2'b11;

    processor_top uut(
        .clk(clk),
        .rst(rst),
        .run(run),
        .opcode(opcode),
        .rx(rx),
        .ry(ry),
        .immediate(immediate),
        .done(done)
    );

    // Clock
    always #5 clk = ~clk;

    // Task to run one instruction
    task run_instruction;
    input [1:0] op;
    input [1:0] dest;
    input [1:0] src;
    input [15:0] imm;
    begin
        // Set instruction fields
        opcode = op;
        rx = dest;
        ry = src;
        immediate = imm;

        // Start instruction on clock edge
        @(posedge clk);
        run = 1'b1;

        @(posedge clk);
        run = 1'b0;

        // Wait until instruction finishes
        wait(done == 1'b1);

        // Wait for done to go back low before next instruction
        @(posedge clk);
        wait(done == 1'b0);
    end
endtask

    initial begin
        $dumpfile("processor.vcd");
        $dumpvars(0, processor_TB);

        clk = 0;
        rst = 1;
        run = 0;
        opcode = 0;
        rx = 0;
        ry = 0;
        immediate = 0;

        #20;
        rst = 0;

        // LDI R0, 5
        run_instruction(LDI, 2'b00, 2'b00, 16'd5);

        // LDI R1, 3
        run_instruction(LDI, 2'b01, 2'b00, 16'd3);

        // ADD R0, R1  => R0 = 5 + 3 = 8
        run_instruction(ADD, 2'b00, 2'b01, 16'd0);

        // SUB R0, R1  => R0 = 8 - 3 = 5
        run_instruction(SUB, 2'b00, 2'b01, 16'd0);

        // MOV R2, R0  => R2 = 5
        run_instruction(MOV, 2'b10, 2'b00, 16'd0);

        #50;
        $finish;
    end

endmodule

LUKE AND JASON/luke/hardware_chat/processor.vcd
$date
	Tue May 12 20:38:10 2026
$end
$version
	Icarus Verilog
$end
$timescale
	1ps
$end
$scope module processor_TB $end
$var wire 1 ! done $end
$var parameter 2 " ADD $end
$var parameter 2 # LDI $end
$var parameter 2 $ MOV $end
$var parameter 2 % SUB $end
$var reg 1 & clk $end
$var reg 16 ' immediate [15:0] $end
$var reg 2 ( opcode [1:0] $end
$var reg 1 ) rst $end
$var reg 1 * run $end
$var reg 2 + rx [1:0] $end
$var reg 2 , ry [1:0] $end
$scope module uut $end
$var wire 1 & clk $end
$var wire 16 - immediate [15:0] $end
$var wire 2 . opcode [1:0] $end
$var wire 1 ) rst $end
$var wire 1 * run $end
$var wire 2 / rx [1:0] $end
$var wire 2 0 ry [1:0] $end
$var wire 1 ! done $end
$var wire 3 1 bus_sel [2:0] $end
$var wire 16 2 bus [15:0] $end
$var wire 16 3 alu_result [15:0] $end
$var wire 1 4 alu_op $end
$var wire 1 5 R2_en $end
$var wire 16 6 R2_data [15:0] $end
$var wire 1 7 R1_en $end
$var wire 16 8 R1_data [15:0] $end
$var wire 1 9 R0_en $end
$var wire 16 : R0_data [15:0] $end
$var wire 1 ; G_en $end
$var wire 16 < G_data [15:0] $end
$var wire 1 = A_en $end
$var wire 16 > A_data [15:0] $end
$scope module A_reg $end
$var wire 1 & clk $end
$var wire 1 ) rst $end
$var wire 1 = en $end
$var wire 16 ? D [15:0] $end
$var reg 16 @ Q [15:0] $end
$upscope $end
$scope module G_reg $end
$var wire 1 & clk $end
$var wire 1 ) rst $end
$var wire 1 ; en $end
$var wire 16 A D [15:0] $end
$var reg 16 B Q [15:0] $end
$upscope $end
$scope module alu $end
$var wire 16 C A [15:0] $end
$var wire 1 4 alu_ctl $end
$var wire 16 D B [15:0] $end
$var reg 16 E Y [15:0] $end
$upscope $end
$scope module controller $end
$var wire 1 & clk $end
$var wire 2 F opcode [1:0] $end
$var wire 1 ) rst $end
$var wire 1 * run $end
$var wire 2 G rx [1:0] $end
$var wire 2 H ry [1:0] $end
$var parameter 2 I ADD $end
$var parameter 3 J BUS_G $end
$var parameter 3 K BUS_IMM $end
$var parameter 3 L BUS_R0 $end
$var parameter 3 M BUS_R1 $end
$var parameter 3 N BUS_R2 $end
$var parameter 3 O DONE $end
$var parameter 3 P EXEC1 $end
$var parameter 3 Q EXEC2 $end
$var parameter 3 R EXEC3 $end
$var parameter 3 S IDLE $end
$var parameter 2 T LDI $end
$var parameter 2 U MOV $end
$var parameter 2 V SUB $end
$var reg 1 = A_en $end
$var reg 1 ; G_en $end
$var reg 1 9 R0_en $end
$var reg 1 7 R1_en $end
$var reg 1 5 R2_en $end
$var reg 1 4 alu_op $end
$var reg 3 W bus_sel [2:0] $end
$var reg 1 ! done $end
$var reg 3 X next_state [2:0] $end
$var reg 3 Y state [2:0] $end
$upscope $end
$scope module mux $end
$var wire 16 Z G_data [15:0] $end
$var wire 3 [ bus_sel [2:0] $end
$var wire 16 \ immediate [15:0] $end
$var wire 16 ] R2_data [15:0] $end
$var wire 16 ^ R1_data [15:0] $end
$var wire 16 _ R0_data [15:0] $end
$var parameter 3 ` BUS_G $end
$var parameter 3 a BUS_IMM $end
$var parameter 3 b BUS_R0 $end
$var parameter 3 c BUS_R1 $end
$var parameter 3 d BUS_R2 $end
$var reg 16 e bus_out [15:0] $end
$upscope $end
$scope module reg_file $end
$var wire 1 9 R0_en $end
$var wire 1 7 R1_en $end
$var wire 1 5 R2_en $end
$var wire 16 f bus_in [15:0] $end
$var wire 1 & clk $end
$var wire 1 ) rst $end
$var wire 16 g R2_out [15:0] $end
$var wire 16 h R1_out [15:0] $end
$var wire 16 i R0_out [15:0] $end
$scope module R0_reg $end
$var wire 16 j D [15:0] $end
$var wire 1 & clk $end
$var wire 1 9 en $end
$var wire 1 ) rst $end
$var reg 16 k Q [15:0] $end
$upscope $end
$scope module R1_reg $end
$var wire 16 l D [15:0] $end
$var wire 1 & clk $end
$var wire 1 7 en $end
$var wire 1 ) rst $end
$var reg 16 m Q [15:0] $end
$upscope $end
$scope module R2_reg $end
$var wire 16 n D [15:0] $end
$var wire 1 & clk $end
$var wire 1 5 en $end
$var wire 1 ) rst $end
$var reg 16 o Q [15:0] $end
$upscope $end
$upscope $end
$upscope $end
$scope task run_instruction $end
$var reg 2 p dest [1:0] $end
$var reg 16 q imm [15:0] $end
$var reg 2 r op [1:0] $end
$var reg 2 s src [1:0] $end
$upscope $end
$upscope $end
$enddefinitions $end
$comment Show the parameter values. $end
$dumpall
b10 d
b1 c
b0 b
b100 a
b11 `
b11 V
b1 U
b0 T
b0 S
b11 R
b10 Q
b1 P
b100 O
b10 N
b1 M
b0 L
b100 K
b11 J
b10 I
b11 %
b1 $
b0 #
b10 "
$end
#0
$dumpvars
bx s
bx r
bx q
bx p
b0 o
b0 n
b0 m
b0 l
b0 k
b0 j
b0 i
b0 h
b0 g
b0 f
b0 e
b0 _
b0 ^
b0 ]
b0 \
b0 [
b0 Z
b0 Y
b0 X
b0 W
b0 H
b0 G
b0 F
b0 E
b0 D
b0 C
b0 B
b0 A
b0 @
b0 ?
b0 >
0=
b0 <
0;
b0 :
09
b0 8
07
b0 6
05
04
b0 3
b0 2
b0 1
b0 0
b0 /
b0 .
b0 -
b0 ,
b0 +
0*
1)
b0 (
b0 '
0&
0!
$end
#5000
1&
#10000
0&
#15000
1&
#20000
0&
b101 '
b101 -
b101 \
b101 q
b0 s
b0 p
b0 r
0)
#25000
b1 X
1*
1&
#30000
0&
#35000
b101 3
b101 A
b101 E
b101 2
b101 ?
b101 D
b101 e
b101 f
b101 j
b101 l
b101 n
19
b100 1
b100 W
b100 [
b1 Y
b100 X
0*
1&
#40000
0&
#45000
1!
09
b0 1
b0 W
b0 [
b0 X
b101 :
b101 _
b101 i
b101 k
b100 Y
1&
#50000
0&
#55000
b11 '
b11 -
b11 \
b1 +
b1 /
b1 G
b11 q
b1 p
0!
b0 Y
1&
#60000
0&
#65000
b1 X
1*
1&
#70000
0&
#75000
b11 3
b11 A
b11 E
b11 2
b11 ?
b11 D
b11 e
b11 f
b11 j
b11 l
b11 n
17
b100 1
b100 W
b100 [
b1 Y
b100 X
0*
1&
#80000
0&
#85000
b101 3
b101 A
b101 E
b101 2
b101 ?
b101 D
b101 e
b101 f
b101 j
b101 l
b101 n
1!
07
b0 1
b0 W
b0 [
b0 X
b11 8
b11 ^
b11 h
b11 m
b100 Y
1&
#90000
0&
#95000
b0 '
b0 -
b0 \
b1 ,
b1 0
b1 H
b0 +
b0 /
b0 G
b10 (
b10 .
b10 F
b0 q
b1 s
b0 p
b10 r
0!
b0 Y
1&
#100000
0&
#105000
b1 X
1*
1&
#110000
0&
#115000
1=
b1 Y
b10 X
0*
1&
#120000
0&
#125000
b11 2
b11 ?
b11 D
b11 e
b11 f
b11 j
b11 l
b11 n
b1000 3
b1000 A
b1000 E
1;
b1 1
b1 W
b1 [
0=
b11 X
b101 >
b101 @
b101 C
b10 Y
1&
#130000
0&
#135000
b1101 3
b1101 A
b1101 E
b1000 2
b1000 ?
b1000 D
b1000 e
b1000 f
b1000 j
b1000 l
b1000 n
19
0;
b11 1
b11 W
b11 [
b100 X
b11 Y
b1000 <
b1000 B
b1000 Z
1&
#140000
0&
#145000
1!
09
b0 1
b0 W
b0 [
b0 X
b1000 :
b1000 _
b1000 i
b1000 k
b100 Y
1&
#150000
0&
#155000
b11 (
b11 .
b11 F
b11 r
0!
b0 Y
1&
#160000
0&
#165000
b1 X
1*
1&
#170000
0&
#175000
1=
b1 Y
b10 X
0*
1&
#180000
0&
#185000
b11 2
b11 ?
b11 D
b11 e
b11 f
b11 j
b11 l
b11 n
b101 3
b101 A
b101 E
1;
14
b1 1
b1 W
b1 [
0=
b11 X
b1000 >
b1000 @
b1000 C
b10 Y
1&
#190000
0&
#195000
b1101 3
b1101 A
b1101 E
b101 2
b101 ?
b101 D
b101 e
b101 f
b101 j
b101 l
b101 n
19
04
0;
b11 1
b11 W
b11 [
b100 X
b11 Y
b101 <
b101 B
b101 Z
1&
#200000
0&
#205000
1!
09
b0 1
b0 W
b0 [
b0 X
b101 :
b101 _
b101 i
b101 k
b100 Y
1&
#210000
0&
#215000
b0 ,
b0 0
b0 H
b10 +
b10 /
b10 G
b1 (
b1 .
b1 F
b0 s
b10 p
b1 r
0!
b0 Y
1&
#220000
0&
#225000
b1 X
1*
1&
#230000
0&
#235000
15
b1 Y
b100 X
0*
1&
#240000
0&
#245000
1!
05
b0 X
b101 6
b101 ]
b101 g
b101 o
b100 Y
1&
#250000
0&
#255000
0!
b0 Y
1&
